{
"meta":{"test_sets":[],"test_metrics":[],"learn_metrics":[{"best_value":"Min","name":"RMSE"}],"launch_mode":"Train","parameters":"","iteration_count":1000,"learn_sets":["learn"],"name":"experiment"},
"iterations":[
{"learn":[3.573904155],"iteration":0,"passed_time":0.0562565745,"remaining_time":56.20031792},
{"learn":[3.45908132],"iteration":1,"passed_time":0.05778308455,"remaining_time":28.83375919},
{"learn":[3.352908518],"iteration":2,"passed_time":0.05943636964,"remaining_time":19.75268684},
{"learn":[3.251033083],"iteration":3,"passed_time":0.06364281564,"remaining_time":15.8470611},
{"learn":[3.157637733],"iteration":4,"passed_time":0.06536063145,"remaining_time":13.00676566},
{"learn":[3.073019032],"iteration":5,"passed_time":0.06744480827,"remaining_time":11.17335657},
{"learn":[3.00026549],"iteration":6,"passed_time":0.06964577444,"remaining_time":9.879750575},
{"learn":[2.928765986],"iteration":7,"passed_time":0.07126312445,"remaining_time":8.836627432},
{"learn":[2.866179449],"iteration":8,"passed_time":0.07295058022,"remaining_time":8.032669445},
{"learn":[2.806429326],"iteration":9,"passed_time":0.07520589795,"remaining_time":7.445383897},
{"learn":[2.752485111],"iteration":10,"passed_time":0.07674803694,"remaining_time":6.90034623},
{"learn":[2.70267795],"iteration":11,"passed_time":0.07818834247,"remaining_time":6.437506864},
{"learn":[2.655893445],"iteration":12,"passed_time":0.07980433525,"remaining_time":6.058990684},
{"learn":[2.616053637],"iteration":13,"passed_time":0.08149294536,"remaining_time":5.739431724},
{"learn":[2.577107617],"iteration":14,"passed_time":0.08348265914,"remaining_time":5.48202795},
{"learn":[2.540630537],"iteration":15,"passed_time":0.08513010817,"remaining_time":5.235501652},
{"learn":[2.508218276],"iteration":16,"passed_time":0.08664049859,"remaining_time":5.009859419},
{"learn":[2.480242483],"iteration":17,"passed_time":0.08807776604,"remaining_time":4.805131458},
{"learn":[2.454748304],"iteration":18,"passed_time":0.08970574414,"remaining_time":4.631649211},
{"learn":[2.4293581],"iteration":19,"passed_time":0.09179369543,"remaining_time":4.497891076},
{"learn":[2.407234424],"iteration":20,"passed_time":0.09324007715,"remaining_time":4.346763596},
{"learn":[2.387406179],"iteration":21,"passed_time":0.09468867218,"remaining_time":4.209341881},
{"learn":[2.36941163],"iteration":22,"passed_time":0.09633096376,"remaining_time":4.091971808},
{"learn":[2.353725418],"iteration":23,"passed_time":0.09787960698,"remaining_time":3.980437351},
{"learn":[2.336510316],"iteration":24,"passed_time":0.1001137207,"remaining_time":3.904435108},
{"learn":[2.322221236],"iteration":25,"passed_time":0.1016391137,"remaining_time":3.807557566},
{"learn":[2.310510548],"iteration":26,"passed_time":0.103132069,"remaining_time":3.71657419},
{"learn":[2.299537934],"iteration":27,"passed_time":0.1058860616,"remaining_time":3.675758997},
{"learn":[2.287843856],"iteration":28,"passed_time":0.1080827063,"remaining_time":3.618907165},
{"learn":[2.277639611],"iteration":29,"passed_time":0.1094879746,"remaining_time":3.540111178},
{"learn":[2.26856344],"iteration":30,"passed_time":0.1108503025,"remaining_time":3.464965906},
{"learn":[2.259564014],"iteration":31,"passed_time":0.1126526106,"remaining_time":3.40774147},
{"learn":[2.252590666],"iteration":32,"passed_time":0.1141424861,"remaining_time":3.344720728},
{"learn":[2.245270758],"iteration":33,"passed_time":0.1163149394,"remaining_time":3.304712691},
{"learn":[2.238144554],"iteration":34,"passed_time":0.1179632968,"remaining_time":3.25241661},
{"learn":[2.231735934],"iteration":35,"passed_time":0.11994219,"remaining_time":3.21178531},
{"learn":[2.225612079],"iteration":36,"passed_time":0.121374206,"remaining_time":3.159009741},
{"learn":[2.220524306],"iteration":37,"passed_time":0.1228526391,"remaining_time":3.110111547},
{"learn":[2.214813446],"iteration":38,"passed_time":0.1245095156,"remaining_time":3.068042166},
{"learn":[2.210073137],"iteration":39,"passed_time":0.1261524231,"remaining_time":3.027658155},
{"learn":[2.204683657],"iteration":40,"passed_time":0.1278337296,"remaining_time":2.990062115},
{"learn":[2.199490061],"iteration":41,"passed_time":0.1292727615,"remaining_time":2.948650131},
{"learn":[2.195548471],"iteration":42,"passed_time":0.1307453585,"remaining_time":2.909844373},
{"learn":[2.19184421],"iteration":43,"passed_time":0.1325414547,"remaining_time":2.879764334},
{"learn":[2.18779027],"iteration":44,"passed_time":0.1347880242,"remaining_time":2.860501403},
{"learn":[2.184751596],"iteration":45,"passed_time":0.1363039062,"remaining_time":2.826824489},
{"learn":[2.1812344],"iteration":46,"passed_time":0.1378788691,"remaining_time":2.79571409},
{"learn":[2.177919863],"iteration":47,"passed_time":0.139393707,"remaining_time":2.764641856},
{"learn":[2.174738219],"iteration":48,"passed_time":0.1418448615,"remaining_time":2.752948231},
{"learn":[2.172060276],"iteration":49,"passed_time":0.14514464,"remaining_time":2.757748161},
{"learn":[2.168697173],"iteration":50,"passed_time":0.1468597309,"remaining_time":2.732742837},
{"learn":[2.16573272],"iteration":51,"passed_time":0.1484710465,"remaining_time":2.706741387},
{"learn":[2.162424342],"iteration":52,"passed_time":0.1499026763,"remaining_time":2.678449706},
{"learn":[2.159309918],"iteration":53,"passed_time":0.1512748075,"remaining_time":2.650110516},
{"learn":[2.157150303],"iteration":54,"passed_time":0.1551985903,"remaining_time":2.666593961},
{"learn":[2.154563467],"iteration":55,"passed_time":0.1570745121,"remaining_time":2.64782749},
{"learn":[2.152296557],"iteration":56,"passed_time":0.1587465582,"remaining_time":2.626280778},
{"learn":[2.149005515],"iteration":57,"passed_time":0.1604051309,"remaining_time":2.605200574},
{"learn":[2.146325884],"iteration":58,"passed_time":0.161916795,"remaining_time":2.582435662},
{"learn":[2.143420279],"iteration":59,"passed_time":0.163343925,"remaining_time":2.559054825},
{"learn":[2.141226997],"iteration":60,"passed_time":0.1647149809,"remaining_time":2.535530607},
{"learn":[2.139276959],"iteration":61,"passed_time":0.1662570781,"remaining_time":2.515308698},
{"learn":[2.13734462],"iteration":62,"passed_time":0.167674718,"remaining_time":2.493828743},
{"learn":[2.134824057],"iteration":63,"passed_time":0.1701191177,"remaining_time":2.487992097},
{"learn":[2.133064793],"iteration":64,"passed_time":0.1716410028,"remaining_time":2.468989809},
{"learn":[2.131490947],"iteration":65,"passed_time":0.1731036921,"remaining_time":2.449679521},
{"learn":[2.129695735],"iteration":66,"passed_time":0.174778114,"remaining_time":2.433850453},
{"learn":[2.12834661],"iteration":67,"passed_time":0.1762100569,"remaining_time":2.41511431},
{"learn":[2.126481735],"iteration":68,"passed_time":0.1777942743,"remaining_time":2.398934339},
{"learn":[2.123904569],"iteration":69,"passed_time":0.179259772,"remaining_time":2.381594114},
{"learn":[2.120604569],"iteration":70,"passed_time":0.1806242192,"remaining_time":2.363378869},
{"learn":[2.118806015],"iteration":71,"passed_time":0.1824800079,"remaining_time":2.351964546},
{"learn":[2.116999019],"iteration":72,"passed_time":0.1840134189,"remaining_time":2.336718346},
{"learn":[2.115359433],"iteration":73,"passed_time":0.1854774654,"remaining_time":2.320974769},
{"learn":[2.113585203],"iteration":74,"passed_time":0.1868836315,"remaining_time":2.304898122},
{"learn":[2.112672609],"iteration":75,"passed_time":0.1883549131,"remaining_time":2.289999206},
{"learn":[2.111537057],"iteration":76,"passed_time":0.1897598682,"remaining_time":2.274654004},
{"learn":[2.10966408],"iteration":77,"passed_time":0.1913817492,"remaining_time":2.26223042},
{"learn":[2.108078346],"iteration":78,"passed_time":0.1928774712,"remaining_time":2.248609506},
{"learn":[2.106653093],"iteration":79,"passed_time":0.1943042776,"remaining_time":2.234499192},
{"learn":[2.104690023],"iteration":80,"passed_time":0.1957549084,"remaining_time":2.220972356},
{"learn":[2.102871655],"iteration":81,"passed_time":0.1983747027,"remaining_time":2.220828989},
{"learn":[2.100196827],"iteration":82,"passed_time":0.1998866592,"remaining_time":2.208386343},
{"learn":[2.098471371],"iteration":83,"passed_time":0.2013287917,"remaining_time":2.195442538},
{"learn":[2.097318313],"iteration":84,"passed_time":0.2027935795,"remaining_time":2.183013238},
{"learn":[2.095982894],"iteration":85,"passed_time":0.2042184022,"remaining_time":2.170414182},
{"learn":[2.094631916],"iteration":86,"passed_time":0.2056335365,"remaining_time":2.157970331},
{"learn":[2.09340008],"iteration":87,"passed_time":0.2075468132,"remaining_time":2.150939701},
{"learn":[2.091671813],"iteration":88,"passed_time":0.209042744,"remaining_time":2.139752133},
{"learn":[2.090696595],"iteration":89,"passed_time":0.2104820055,"remaining_time":2.128206945},
{"learn":[2.089641768],"iteration":90,"passed_time":0.2119173416,"remaining_time":2.116844654},
{"learn":[2.088698397],"iteration":91,"passed_time":0.2137490228,"remaining_time":2.10960992},
{"learn":[2.086680647],"iteration":92,"passed_time":0.215220012,"remaining_time":2.098973665},
{"learn":[2.085503334],"iteration":93,"passed_time":0.216810046,"remaining_time":2.089679805},
{"learn":[2.084261393],"iteration":94,"passed_time":0.2183689936,"remaining_time":2.080251992},
{"learn":[2.083026844],"iteration":95,"passed_time":0.2198015839,"remaining_time":2.069798248},
{"learn":[2.081694838],"iteration":96,"passed_time":0.2212901752,"remaining_time":2.060051837},
{"learn":[2.079838281],"iteration":97,"passed_time":0.2228140543,"remaining_time":2.050798745},
{"learn":[2.079127623],"iteration":98,"passed_time":0.2246123221,"remaining_time":2.044199012},
{"learn":[2.077479431],"iteration":99,"passed_time":0.2260758048,"remaining_time":2.034682244},
{"learn":[2.076539411],"iteration":100,"passed_time":0.2275096584,"remaining_time":2.025061216},
{"learn":[2.07522072],"iteration":101,"passed_time":0.2290656515,"remaining_time":2.016676029},
{"learn":[2.074218751],"iteration":102,"passed_time":0.2304963207,"remaining_time":2.007332036},
{"learn":[2.073037276],"iteration":103,"passed_time":0.2319165811,"remaining_time":1.998050545},
{"learn":[2.072132844],"iteration":104,"passed_time":0.233636944,"remaining_time":1.991476808},
{"learn":[2.070839319],"iteration":105,"passed_time":0.2350635207,"remaining_time":1.982516863},
{"learn":[2.069579854],"iteration":106,"passed_time":0.2365443967,"remaining_time":1.9741509},
{"learn":[2.068880841],"iteration":107,"passed_time":0.2380387615,"remaining_time":1.966023845},
{"learn":[2.068104996],"iteration":108,"passed_time":0.2394819798,"remaining_time":1.957600404},
{"learn":[2.067097275],"iteration":109,"passed_time":0.2410794935,"remaining_time":1.950552266},
{"learn":[2.065949366],"iteration":110,"passed_time":0.2425963046,"remaining_time":1.942955989},
{"learn":[2.06510659],"iteration":111,"passed_time":0.2440347205,"remaining_time":1.934846712},
{"learn":[2.063172579],"iteration":112,"passed_time":0.2456817623,"remaining_time":1.928493126},
{"learn":[2.062141183],"iteration":113,"passed_time":0.2472391753,"remaining_time":1.92152552},
{"learn":[2.060935486],"iteration":114,"passed_time":0.2487263885,"remaining_time":1.914111773},
{"learn":[2.059237052],"iteration":115,"passed_time":0.2503022806,"remaining_time":1.907476001},
{"learn":[2.058543647],"iteration":116,"passed_time":0.2517244516,"remaining_time":1.899766588},
{"learn":[2.057622946],"iteration":117,"passed_time":0.2534156032,"remaining_time":1.894174254},
{"learn":[2.056613019],"iteration":118,"passed_time":0.2546703973,"remaining_time":1.885416975},
{"learn":[2.055610575],"iteration":119,"passed_time":0.2561599908,"remaining_time":1.8785066},
{"learn":[2.054804365],"iteration":120,"passed_time":0.2578031956,"remaining_time":1.872801727},
{"learn":[2.054176743],"iteration":121,"passed_time":0.2593000869,"remaining_time":1.866110461},
{"learn":[2.053509232],"iteration":122,"passed_time":0.2609391524,"remaining_time":1.860517371},
{"learn":[2.05290076],"iteration":123,"passed_time":0.262382778,"remaining_time":1.853607367},
{"learn":[2.052093224],"iteration":124,"passed_time":0.2638243676,"remaining_time":1.846770573},
{"learn":[2.050337603],"iteration":125,"passed_time":0.2653225952,"remaining_time":1.840412288},
{"learn":[2.049811924],"iteration":126,"passed_time":0.2670854708,"remaining_time":1.835949733},
{"learn":[2.048777456],"iteration":127,"passed_time":0.268806544,"remaining_time":1.831244581},
{"learn":[2.047961895],"iteration":128,"passed_time":0.2702007144,"remaining_time":1.824378467},
{"learn":[2.047208272],"iteration":129,"passed_time":0.271614575,"remaining_time":1.817728309},
{"learn":[2.04545576],"iteration":130,"passed_time":0.273133589,"remaining_time":1.81185564},
{"learn":[2.044499558],"iteration":131,"passed_time":0.2750563245,"remaining_time":1.80870371},
{"learn":[2.043707053],"iteration":132,"passed_time":0.2766406634,"remaining_time":1.803364324},
{"learn":[2.042584252],"iteration":133,"passed_time":0.2781174782,"remaining_time":1.79738609},
{"learn":[2.040543364],"iteration":134,"passed_time":0.2795861497,"remaining_time":1.791422366},
{"learn":[2.039292642],"iteration":135,"passed_time":0.2812841911,"remaining_time":1.78698192},
{"learn":[2.037777964],"iteration":136,"passed_time":0.2831817658,"remaining_time":1.783838423},
{"learn":[2.036875026],"iteration":137,"passed_time":0.2847044026,"remaining_time":1.778370978},
{"learn":[2.035535533],"iteration":138,"passed_time":0.2861461802,"remaining_time":1.772459432},
{"learn":[2.034977682],"iteration":139,"passed_time":0.287613484,"remaining_time":1.766768544},
{"learn":[2.034011264],"iteration":140,"passed_time":0.2896405377,"remaining_time":1.764547673},
{"learn":[2.032823106],"iteration":141,"passed_time":0.2914316018,"remaining_time":1.760903622},
{"learn":[2.031440838],"iteration":142,"passed_time":0.2928962747,"remaining_time":1.755329422},
{"learn":[2.030021983],"iteration":143,"passed_time":0.294392811,"remaining_time":1.75000171},
{"learn":[2.028077853],"iteration":144,"passed_time":0.2963299331,"remaining_time":1.747324778},
{"learn":[2.027357617],"iteration":145,"passed_time":0.2978948526,"remaining_time":1.74248085},
{"learn":[2.026285272],"iteration":146,"passed_time":0.2995352336,"remaining_time":1.738119417},
{"learn":[2.02465451],"iteration":147,"passed_time":0.3011035774,"remaining_time":1.733380054},
{"learn":[2.022594245],"iteration":148,"passed_time":0.3032960355,"remaining_time":1.732247827},
{"learn":[2.021994123],"iteration":149,"passed_time":0.3049735001,"remaining_time":1.728183167},
{"learn":[2.021274428],"iteration":150,"passed_time":0.3064656724,"remaining_time":1.723108317},
{"learn":[2.019935021],"iteration":151,"passed_time":0.3098059741,"remaining_time":1.728391224},
{"learn":[2.018809355],"iteration":152,"passed_time":0.3120945124,"remaining_time":1.727738902},
{"learn":[2.017573721],"iteration":153,"passed_time":0.3135476072,"remaining_time":1.722475816},
{"learn":[2.016511696],"iteration":154,"passed_time":0.3152562147,"remaining_time":1.718654848},
{"learn":[2.014892239],"iteration":155,"passed_time":0.3172513111,"remaining_time":1.71641094},
{"learn":[2.013455889],"iteration":156,"passed_time":0.3192116529,"remaining_time":1.713983588},
{"learn":[2.011576784],"iteration":157,"passed_time":0.3214218221,"remaining_time":1.712893507},
{"learn":[2.009393843],"iteration":158,"passed_time":0.3232380887,"remaining_time":1.709705865},
{"learn":[2.007502829],"iteration":159,"passed_time":0.3273841682,"remaining_time":1.718766883},
{"learn":[2.006729496],"iteration":160,"passed_time":0.3295993017,"remaining_time":1.71760133},
{"learn":[2.005518737],"iteration":161,"passed_time":0.3313010292,"remaining_time":1.713767052},
{"learn":[2.004457006],"iteration":162,"passed_time":0.3331439914,"remaining_time":1.710684177},
{"learn":[2.003375719],"iteration":163,"passed_time":0.3362485546,"remaining_time":1.71404751},
{"learn":[2.002833994],"iteration":164,"passed_time":0.3376816251,"remaining_time":1.708873679},
{"learn":[2.001824816],"iteration":165,"passed_time":0.3401864421,"remaining_time":1.709129474},
{"learn":[2.000791522],"iteration":166,"passed_time":0.3424084512,"remaining_time":1.707941556},
{"learn":[1.999905291],"iteration":167,"passed_time":0.3457634693,"remaining_time":1.712352419},
{"learn":[1.999417442],"iteration":168,"passed_time":0.347332095,"remaining_time":1.707887402},
{"learn":[1.998711323],"iteration":169,"passed_time":0.3487336257,"remaining_time":1.702640643},
{"learn":[1.997390711],"iteration":170,"passed_time":0.3529892648,"remaining_time":1.711275442},
{"learn":[1.996502385],"iteration":171,"passed_time":0.3547807305,"remaining_time":1.707897935},
{"learn":[1.995815715],"iteration":172,"passed_time":0.3563366401,"remaining_time":1.703412724},
{"learn":[1.994197806],"iteration":173,"passed_time":0.3599711152,"remaining_time":1.708828397},
{"learn":[1.993728308],"iteration":174,"passed_time":0.3620043033,"remaining_time":1.706591715},
{"learn":[1.992084446],"iteration":175,"passed_time":0.3637044647,"remaining_time":1.702798176},
{"learn":[1.990442881],"iteration":176,"passed_time":0.365377346,"remaining_time":1.698901445},
{"learn":[1.989198984],"iteration":177,"passed_time":0.3690903626,"remaining_time":1.704451},
{"learn":[1.988451896],"iteration":178,"passed_time":0.3706889516,"remaining_time":1.700199046},
{"learn":[1.987567354],"iteration":179,"passed_time":0.3726034499,"remaining_time":1.697415716},
{"learn":[1.986459313],"iteration":180,"passed_time":0.3741845307,"remaining_time":1.693133318},
{"learn":[1.985543335],"iteration":181,"passed_time":0.3775070848,"remaining_time":1.696707667},
{"learn":[1.984564657],"iteration":182,"passed_time":0.3794924509,"remaining_time":1.694236789},
{"learn":[1.983532376],"iteration":183,"passed_time":0.3812707467,"remaining_time":1.690852876},
{"learn":[1.98238257],"iteration":184,"passed_time":0.3840089061,"remaining_time":1.691714911},
{"learn":[1.981147761],"iteration":185,"passed_time":0.3855255815,"remaining_time":1.687192599},
{"learn":[1.980025139],"iteration":186,"passed_time":0.3870956271,"remaining_time":1.682934464},
{"learn":[1.9794812],"iteration":187,"passed_time":0.3892891494,"remaining_time":1.681397815},
{"learn":[1.978509777],"iteration":188,"passed_time":0.3910715481,"remaining_time":1.678090082},
{"learn":[1.977748799],"iteration":189,"passed_time":0.392868135,"remaining_time":1.674858891},
{"learn":[1.977020183],"iteration":190,"passed_time":0.3949072263,"remaining_time":1.672669875},
{"learn":[1.97607048],"iteration":191,"passed_time":0.3963634949,"remaining_time":1.668029708},
{"learn":[1.975189382],"iteration":192,"passed_time":0.3978738226,"remaining_time":1.663648574},
{"learn":[1.974325461],"iteration":193,"passed_time":0.3997838316,"remaining_time":1.660957568},
{"learn":[1.973465354],"iteration":194,"passed_time":0.4017384306,"remaining_time":1.658458649},
{"learn":[1.972720191],"iteration":195,"passed_time":0.4032570583,"remaining_time":1.654176912},
{"learn":[1.971992522],"iteration":196,"passed_time":0.4046460295,"remaining_time":1.649394729},
{"learn":[1.970887089],"iteration":197,"passed_time":0.4061159016,"remaining_time":1.64497451},
{"learn":[1.970132231],"iteration":198,"passed_time":0.4077895346,"remaining_time":1.641404106},
{"learn":[1.969374617],"iteration":199,"passed_time":0.409363261,"remaining_time":1.637453044},
{"learn":[1.968555195],"iteration":200,"passed_time":0.4108714277,"remaining_time":1.633265028},
{"learn":[1.967508017],"iteration":201,"passed_time":0.412286635,"remaining_time":1.628736311},
{"learn":[1.966988104],"iteration":202,"passed_time":0.413755484,"remaining_time":1.624448871},
{"learn":[1.966393087],"iteration":203,"passed_time":0.4159130399,"remaining_time":1.622876371},
{"learn":[1.965617935],"iteration":204,"passed_time":0.4174484972,"remaining_time":1.618885635},
{"learn":[1.964731588],"iteration":205,"passed_time":0.4189153893,"remaining_time":1.614654462},
{"learn":[1.964212286],"iteration":206,"passed_time":0.4203018758,"remaining_time":1.610141969},
{"learn":[1.963081904],"iteration":207,"passed_time":0.4222149333,"remaining_time":1.607664554},
{"learn":[1.962437254],"iteration":208,"passed_time":0.4237287481,"remaining_time":1.60368153},
{"learn":[1.961081786],"iteration":209,"passed_time":0.4253207702,"remaining_time":1.600016231},
{"learn":[1.960634973],"iteration":210,"passed_time":0.4266911266,"remaining_time":1.595541701},
{"learn":[1.95993019],"iteration":211,"passed_time":0.4281301166,"remaining_time":1.591351566},
{"learn":[1.958952844],"iteration":212,"passed_time":0.4295616733,"remaining_time":1.587159798},
{"learn":[1.957914578],"iteration":213,"passed_time":0.4310954184,"remaining_time":1.583369154},
{"learn":[1.956729983],"iteration":214,"passed_time":0.4327882136,"remaining_time":1.580180222},
{"learn":[1.955884393],"iteration":215,"passed_time":0.4346442573,"remaining_time":1.577597675},
{"learn":[1.954791571],"iteration":216,"passed_time":0.4362505825,"remaining_time":1.574120766},
{"learn":[1.953727191],"iteration":217,"passed_time":0.4378275604,"remaining_time":1.570555744},
{"learn":[1.953010017],"iteration":218,"passed_time":0.439222211,"remaining_time":1.566358661},
{"learn":[1.951119462],"iteration":219,"passed_time":0.4407252411,"remaining_time":1.562571309},
{"learn":[1.950506569],"iteration":220,"passed_time":0.4424406139,"remaining_time":1.559553114},
{"learn":[1.949753335],"iteration":221,"passed_time":0.4442914271,"remaining_time":1.557021308},
{"learn":[1.949103469],"iteration":222,"passed_time":0.4457343949,"remaining_time":1.553074551},
{"learn":[1.947786811],"iteration":223,"passed_time":0.4472126296,"remaining_time":1.549272324},
{"learn":[1.946779118],"iteration":224,"passed_time":0.4486976354,"remaining_time":1.545514078},
{"learn":[1.945264253],"iteration":225,"passed_time":0.4504197258,"remaining_time":1.54258791},
{"learn":[1.944769507],"iteration":226,"passed_time":0.4523141684,"remaining_time":1.540259261},
{"learn":[1.943758717],"iteration":227,"passed_time":0.4538250809,"remaining_time":1.5366358},
{"learn":[1.942977457],"iteration":228,"passed_time":0.4552211827,"remaining_time":1.532644244},
{"learn":[1.942342719],"iteration":229,"passed_time":0.456939082,"remaining_time":1.529752579},
{"learn":[1.941721763],"iteration":230,"passed_time":0.4585878987,"remaining_time":1.5266411},
{"learn":[1.940691162],"iteration":231,"passed_time":0.4601116317,"remaining_time":1.52312816},
{"learn":[1.939230734],"iteration":232,"passed_time":0.4615436895,"remaining_time":1.519330514},
{"learn":[1.938561828],"iteration":233,"passed_time":0.4631569678,"remaining_time":1.516146313},
{"learn":[1.938010729],"iteration":234,"passed_time":0.4650921063,"remaining_time":1.51402324},
{"learn":[1.936900327],"iteration":235,"passed_time":0.4669508286,"remaining_time":1.511654377},
{"learn":[1.936340942],"iteration":236,"passed_time":0.4702223716,"remaining_time":1.513838268},
{"learn":[1.935708614],"iteration":237,"passed_time":0.4731843896,"remaining_time":1.514985315},
{"learn":[1.935032917],"iteration":238,"passed_time":0.4755445162,"remaining_time":1.514181493},
{"learn":[1.934346699],"iteration":239,"passed_time":0.4776734243,"remaining_time":1.51263251},
{"learn":[1.933453715],"iteration":240,"passed_time":0.4793183677,"remaining_time":1.509554527},
{"learn":[1.932714227],"iteration":241,"passed_time":0.4813567282,"remaining_time":1.507720661},
{"learn":[1.932049601],"iteration":242,"passed_time":0.4856942029,"remaining_time":1.513047373},
{"learn":[1.930970749],"iteration":243,"passed_time":0.4879175632,"remaining_time":1.511744581},
{"learn":[1.930118788],"iteration":244,"passed_time":0.4895740639,"remaining_time":1.508687421},
{"learn":[1.928909488],"iteration":245,"passed_time":0.4923650356,"remaining_time":1.509118849},
{"learn":[1.928454332],"iteration":246,"passed_time":0.4950963104,"remaining_time":1.509342193},
{"learn":[1.927874972],"iteration":247,"passed_time":0.4966208577,"remaining_time":1.505882601},
{"learn":[1.927450824],"iteration":248,"passed_time":0.4981499256,"remaining_time":1.502452185},
{"learn":[1.926203981],"iteration":249,"passed_time":0.5015199721,"remaining_time":1.504559916},
{"learn":[1.925455295],"iteration":250,"passed_time":0.5046306115,"remaining_time":1.505849912},
{"learn":[1.924434493],"iteration":251,"passed_time":0.5065380939,"remaining_time":1.503533707},
{"learn":[1.923923342],"iteration":252,"passed_time":0.5099911404,"remaining_time":1.505784118},
{"learn":[1.923479],"iteration":253,"passed_time":0.5124774679,"remaining_time":1.505150358},
{"learn":[1.922778126],"iteration":254,"passed_time":0.5143870279,"remaining_time":1.502817003},
{"learn":[1.922114889],"iteration":255,"passed_time":0.515777064,"remaining_time":1.498977092},
{"learn":[1.921731848],"iteration":256,"passed_time":0.5176321674,"remaining_time":1.49650078},
{"learn":[1.921051136],"iteration":257,"passed_time":0.5211557477,"remaining_time":1.498827771},
{"learn":[1.920369768],"iteration":258,"passed_time":0.5230834215,"remaining_time":1.496543688},
{"learn":[1.919375716],"iteration":259,"passed_time":0.526056156,"remaining_time":1.497236752},
{"learn":[1.918668216],"iteration":260,"passed_time":0.5290629685,"remaining_time":1.497998214},
{"learn":[1.91781282],"iteration":261,"passed_time":0.5305681702,"remaining_time":1.494501182},
{"learn":[1.916644074],"iteration":262,"passed_time":0.532013059,"remaining_time":1.490850283},
{"learn":[1.915842793],"iteration":263,"passed_time":0.5338124334,"remaining_time":1.48820436},
{"learn":[1.914385433],"iteration":264,"passed_time":0.5363591259,"remaining_time":1.487637576},
{"learn":[1.913293298],"iteration":265,"passed_time":0.5379615047,"remaining_time":1.484450167},
{"learn":[1.912419612],"iteration":266,"passed_time":0.5405201304,"remaining_time":1.483899834},
{"learn":[1.91107332],"iteration":267,"passed_time":0.5438078143,"remaining_time":1.485325821},
{"learn":[1.90953133],"iteration":268,"passed_time":0.5460260583,"remaining_time":1.48381059},
{"learn":[1.909224167],"iteration":269,"passed_time":0.5474900212,"remaining_time":1.480250798},
{"learn":[1.907676981],"iteration":270,"passed_time":0.5490702251,"remaining_time":1.477019166},
{"learn":[1.906897103],"iteration":271,"passed_time":0.5512359453,"remaining_time":1.475366795},
{"learn":[1.906248531],"iteration":272,"passed_time":0.5528596011,"remaining_time":1.472267143},
{"learn":[1.90546179],"iteration":273,"passed_time":0.5548814452,"remaining_time":1.470233318},
{"learn":[1.904250576],"iteration":274,"passed_time":0.5568444798,"remaining_time":1.468044538},
{"learn":[1.903728999],"iteration":275,"passed_time":0.5593451319,"remaining_time":1.467267665},
{"learn":[1.903017401],"iteration":276,"passed_time":0.5610050987,"remaining_time":1.464284066},
{"learn":[1.902601409],"iteration":277,"passed_time":0.5629242943,"remaining_time":1.461983239},
{"learn":[1.901136689],"iteration":278,"passed_time":0.5646456807,"remaining_time":1.459173963},
{"learn":[1.900309864],"iteration":279,"passed_time":0.5684100218,"remaining_time":1.46162577},
{"learn":[1.899774562],"iteration":280,"passed_time":0.5704281806,"remaining_time":1.459565345},
{"learn":[1.899009607],"iteration":281,"passed_time":0.5721322884,"remaining_time":1.456705614},
{"learn":[1.897864213],"iteration":282,"passed_time":0.5757727667,"remaining_time":1.458759978},
{"learn":[1.897059734],"iteration":283,"passed_time":0.5781471859,"remaining_time":1.457582342},
{"learn":[1.896537167],"iteration":284,"passed_time":0.579930399,"remaining_time":1.454913106},
{"learn":[1.895302353],"iteration":285,"passed_time":0.5815090681,"remaining_time":1.451739422},
{"learn":[1.894342619],"iteration":286,"passed_time":0.5835703657,"remaining_time":1.449775856},
{"learn":[1.893547615],"iteration":287,"passed_time":0.5860765816,"remaining_time":1.448911549},
{"learn":[1.89239556],"iteration":288,"passed_time":0.587728593,"remaining_time":1.445934359},
{"learn":[1.891900034],"iteration":289,"passed_time":0.589291247,"remaining_time":1.442747536},
{"learn":[1.891418232],"iteration":290,"passed_time":0.5907987037,"remaining_time":1.439437391},
{"learn":[1.890783971],"iteration":291,"passed_time":0.5935889864,"remaining_time":1.439250008},
{"learn":[1.890348085],"iteration":292,"passed_time":0.595699217,"remaining_time":1.437403913},
{"learn":[1.889335647],"iteration":293,"passed_time":0.5973564485,"remaining_time":1.434468206},
{"learn":[1.888818685],"iteration":294,"passed_time":0.5992324426,"remaining_time":1.432063973},
{"learn":[1.888030461],"iteration":295,"passed_time":0.6013181493,"remaining_time":1.430162085},
{"learn":[1.887275865],"iteration":296,"passed_time":0.6033645598,"remaining_time":1.428165945},
{"learn":[1.886690911],"iteration":297,"passed_time":0.6053225936,"remaining_time":1.425961278},
{"learn":[1.88562692],"iteration":298,"passed_time":0.6067844059,"remaining_time":1.422594878},
{"learn":[1.884805262],"iteration":299,"passed_time":0.609760461,"remaining_time":1.422774409},
{"learn":[1.884010261],"iteration":300,"passed_time":0.6121983252,"remaining_time":1.421683154},
{"learn":[1.883096201],"iteration":301,"passed_time":0.6146452201,"remaining_time":1.420603853},
{"learn":[1.88221791],"iteration":302,"passed_time":0.6179719607,"remaining_time":1.421539461},
{"learn":[1.881743232],"iteration":303,"passed_time":0.620532538,"remaining_time":1.420692916},
{"learn":[1.880673281],"iteration":304,"passed_time":0.6220870068,"remaining_time":1.417542524},
{"learn":[1.879694921],"iteration":305,"passed_time":0.6236073363,"remaining_time":1.414325135},
{"learn":[1.878910645],"iteration":306,"passed_time":0.625396709,"remaining_time":1.411726122},
{"learn":[1.878078818],"iteration":307,"passed_time":0.6268226489,"remaining_time":1.408315822},
{"learn":[1.877142279],"iteration":308,"passed_time":0.6283607475,"remaining_time":1.40516918},
{"learn":[1.876445106],"iteration":309,"passed_time":0.6298291058,"remaining_time":1.401877687},
{"learn":[1.876064412],"iteration":310,"passed_time":0.6313673715,"remaining_time":1.398752794},
{"learn":[1.874926029],"iteration":311,"passed_time":0.6348876834,"remaining_time":1.400008738},
{"learn":[1.874380896],"iteration":312,"passed_time":0.6368691658,"remaining_time":1.397856603},
{"learn":[1.87340468],"iteration":313,"passed_time":0.6387424469,"remaining_time":1.395469167},
{"learn":[1.872094959],"iteration":314,"passed_time":0.6423478455,"remaining_time":1.396851664},
{"learn":[1.871351884],"iteration":315,"passed_time":0.6454589032,"remaining_time":1.397132563},
{"learn":[1.870723002],"iteration":316,"passed_time":0.6470222775,"remaining_time":1.394057462},
{"learn":[1.869797659],"iteration":317,"passed_time":0.6486627107,"remaining_time":1.391157134},
{"learn":[1.869117407],"iteration":318,"passed_time":0.6509737163,"remaining_time":1.389696241},
{"learn":[1.868434289],"iteration":319,"passed_time":0.6524525044,"remaining_time":1.386461572},
{"learn":[1.867727798],"iteration":320,"passed_time":0.6539631349,"remaining_time":1.383305198},
{"learn":[1.867252719],"iteration":321,"passed_time":0.6558730081,"remaining_time":1.380999688},
{"learn":[1.866479021],"iteration":322,"passed_time":0.6575805613,"remaining_time":1.37827257},
{"learn":[1.866018673],"iteration":323,"passed_time":0.6591419512,"remaining_time":1.375246787},
{"learn":[1.865503337],"iteration":324,"passed_time":0.6606243098,"remaining_time":1.372065874},
{"learn":[1.864614524],"iteration":325,"passed_time":0.6622551694,"remaining_time":1.369202405},
{"learn":[1.864297347],"iteration":326,"passed_time":0.6636291172,"remaining_time":1.365817724},
{"learn":[1.863918322],"iteration":327,"passed_time":0.6651345172,"remaining_time":1.362714621},
{"learn":[1.863512219],"iteration":328,"passed_time":0.6668770762,"remaining_time":1.360104918},
{"learn":[1.862862464],"iteration":329,"passed_time":0.668336101,"remaining_time":1.356924811},
{"learn":[1.862285594],"iteration":330,"passed_time":0.6698727275,"remaining_time":1.353911948},
{"learn":[1.861179053],"iteration":331,"passed_time":0.6713830136,"remaining_time":1.350854979},
{"learn":[1.860350306],"iteration":332,"passed_time":0.6729320744,"remaining_time":1.347884966},
{"learn":[1.859776534],"iteration":333,"passed_time":0.6745523163,"remaining_time":1.345065397},
{"learn":[1.859388342],"iteration":334,"passed_time":0.6761718588,"remaining_time":1.3422516},
{"learn":[1.859091467],"iteration":335,"passed_time":0.6776271251,"remaining_time":1.339120271},
{"learn":[1.85851584],"iteration":336,"passed_time":0.6790169419,"remaining_time":1.335870126},
{"learn":[1.85780938],"iteration":337,"passed_time":0.6804235466,"remaining_time":1.332663869},
{"learn":[1.857348184],"iteration":338,"passed_time":0.6818608453,"remaining_time":1.329528079},
{"learn":[1.856595897],"iteration":339,"passed_time":0.683971671,"remaining_time":1.327709714},
{"learn":[1.85621851],"iteration":340,"passed_time":0.6854199007,"remaining_time":1.324609134},
{"learn":[1.855153378],"iteration":341,"passed_time":0.6870003029,"remaining_time":1.321772513},
{"learn":[1.854817735],"iteration":342,"passed_time":0.6884233926,"remaining_time":1.318641892},
{"learn":[1.853717842],"iteration":343,"passed_time":0.6904837923,"remaining_time":1.316736534},
{"learn":[1.853183052],"iteration":344,"passed_time":0.6921359087,"remaining_time":1.314055131},
{"learn":[1.852238038],"iteration":345,"passed_time":0.6935840757,"remaining_time":1.310994178},
{"learn":[1.851406466],"iteration":346,"passed_time":0.6951005737,"remaining_time":1.308071108},
{"learn":[1.850469607],"iteration":347,"passed_time":0.6965394489,"remaining_time":1.305010692},
{"learn":[1.850026304],"iteration":348,"passed_time":0.6982363008,"remaining_time":1.302440779},
{"learn":[1.849335437],"iteration":349,"passed_time":0.6997827307,"remaining_time":1.2995965},
{"learn":[1.848293336],"iteration":350,"passed_time":0.7013466375,"remaining_time":1.296791931},
{"learn":[1.847903518],"iteration":351,"passed_time":0.7027908685,"remaining_time":1.293774099},
{"learn":[1.847275022],"iteration":352,"passed_time":0.7042277184,"remaining_time":1.290751654},
{"learn":[1.846583518],"iteration":353,"passed_time":0.7056688278,"remaining_time":1.28774594},
{"learn":[1.845914188],"iteration":354,"passed_time":0.7071204191,"remaining_time":1.284768085},
{"learn":[1.845514464],"iteration":355,"passed_time":0.7089008447,"remaining_time":1.282393663},
{"learn":[1.84499321],"iteration":356,"passed_time":0.7103272752,"remaining_time":1.27938498},
{"learn":[1.844503107],"iteration":357,"passed_time":0.7117595314,"remaining_time":1.276395584},
{"learn":[1.844237702],"iteration":358,"passed_time":0.7132008705,"remaining_time":1.273431081},
{"learn":[1.843830356],"iteration":359,"passed_time":0.7146,"remaining_time":1.2704},
{"learn":[1.843255143],"iteration":360,"passed_time":0.7164867169,"remaining_time":1.268241031},
{"learn":[1.842638311],"iteration":361,"passed_time":0.7179953743,"remaining_time":1.265417262},
{"learn":[1.841931674],"iteration":362,"passed_time":0.7193926767,"remaining_time":1.262405331},
{"learn":[1.841290696],"iteration":363,"passed_time":0.7208163197,"remaining_time":1.259448295},
{"learn":[1.840680641],"iteration":364,"passed_time":0.7222996597,"remaining_time":1.256603517},
{"learn":[1.840292459],"iteration":365,"passed_time":0.7235869853,"remaining_time":1.253426636},
{"learn":[1.839861075],"iteration":366,"passed_time":0.7253128707,"remaining_time":1.251016477},
{"learn":[1.839004879],"iteration":367,"passed_time":0.7267317425,"remaining_time":1.248082775},
{"learn":[1.838419051],"iteration":368,"passed_time":0.7283063714,"remaining_time":1.245423632},
{"learn":[1.837614963],"iteration":369,"passed_time":0.7298189647,"remaining_time":1.242664724},
{"learn":[1.837070012],"iteration":370,"passed_time":0.7312234917,"remaining_time":1.239729316},
{"learn":[1.83631502],"iteration":371,"passed_time":0.7330011088,"remaining_time":1.237431979},
{"learn":[1.835565771],"iteration":372,"passed_time":0.7344520738,"remaining_time":1.234588338},
{"learn":[1.835261043],"iteration":373,"passed_time":0.7358827952,"remaining_time":1.231718262},
{"learn":[1.83491535],"iteration":374,"passed_time":0.7373011451,"remaining_time":1.228835242},
{"learn":[1.834176258],"iteration":375,"passed_time":0.7387404588,"remaining_time":1.225994804},
{"learn":[1.833770459],"iteration":376,"passed_time":0.7401897011,"remaining_time":1.223178206},
{"learn":[1.832958089],"iteration":377,"passed_time":0.7420884876,"remaining_time":1.22110857},
{"learn":[1.832531623],"iteration":378,"passed_time":0.7438079738,"remaining_time":1.218746047},
{"learn":[1.831634917],"iteration":379,"passed_time":0.7453770067,"remaining_time":1.216141432},
{"learn":[1.830903064],"iteration":380,"passed_time":0.746811852,"remaining_time":1.213324243},
{"learn":[1.830515197],"iteration":381,"passed_time":0.7482631928,"remaining_time":1.210540977},
{"learn":[1.829942526],"iteration":382,"passed_time":0.7498604351,"remaining_time":1.207999709},
{"learn":[1.829276273],"iteration":383,"passed_time":0.7512973997,"remaining_time":1.205206245},
{"learn":[1.828603883],"iteration":384,"passed_time":0.752781648,"remaining_time":1.20249536},
{"learn":[1.828075896],"iteration":385,"passed_time":0.7542262026,"remaining_time":1.19972769},
{"learn":[1.827723976],"iteration":386,"passed_time":0.7556166877,"remaining_time":1.196881213},
{"learn":[1.82719776],"iteration":387,"passed_time":0.7570383471,"remaining_time":1.194091413},
{"learn":[1.826538762],"iteration":388,"passed_time":0.7585974409,"remaining_time":1.191524515},
{"learn":[1.826038028],"iteration":389,"passed_time":0.7601972089,"remaining_time":1.189026404},
{"learn":[1.825416558],"iteration":390,"passed_time":0.7616010783,"remaining_time":1.186227766},
{"learn":[1.824782296],"iteration":391,"passed_time":0.7630596228,"remaining_time":1.183521048},
{"learn":[1.824145916],"iteration":392,"passed_time":0.7644874106,"remaining_time":1.180773176},
{"learn":[1.823747269],"iteration":393,"passed_time":0.765952334,"remaining_time":1.178089123},
{"learn":[1.82302713],"iteration":394,"passed_time":0.7673043261,"remaining_time":1.175238272},
{"learn":[1.82242281],"iteration":395,"passed_time":0.7687312056,"remaining_time":1.172509213},
{"learn":[1.821832614],"iteration":396,"passed_time":0.7701477388,"remaining_time":1.169770999},
{"learn":[1.821199293],"iteration":397,"passed_time":0.7715691163,"remaining_time":1.167046754},
{"learn":[1.82032381],"iteration":398,"passed_time":0.7729868085,"remaining_time":1.164323488},
{"learn":[1.819697031],"iteration":399,"passed_time":0.7746726042,"remaining_time":1.162008906},
{"learn":[1.818624409],"iteration":400,"passed_time":0.7761212932,"remaining_time":1.159343278},
{"learn":[1.817702836],"iteration":401,"passed_time":0.777635369,"remaining_time":1.156780972},
{"learn":[1.817044782],"iteration":402,"passed_time":0.7790899776,"remaining_time":1.154135773},
{"learn":[1.816436557],"iteration":403,"passed_time":0.7805553396,"remaining_time":1.151512333},
{"learn":[1.815661252],"iteration":404,"passed_time":0.7820540474,"remaining_time":1.148943601},
{"learn":[1.81529234],"iteration":405,"passed_time":0.7835481303,"remaining_time":1.146373373},
{"learn":[1.814741014],"iteration":406,"passed_time":0.7849447959,"remaining_time":1.143666496},
{"learn":[1.814073101],"iteration":407,"passed_time":0.7864048751,"remaining_time":1.141058054},
{"learn":[1.813612223],"iteration":408,"passed_time":0.7878617388,"remaining_time":1.138450581},
{"learn":[1.813001592],"iteration":409,"passed_time":0.7893107514,"remaining_time":1.135837423},
{"learn":[1.812632737],"iteration":410,"passed_time":0.7908180202,"remaining_time":1.133313416},
{"learn":[1.811840829],"iteration":411,"passed_time":0.792350335,"remaining_time":1.13083009},
{"learn":[1.811286561],"iteration":412,"passed_time":0.7937911521,"remaining_time":1.128221323},
{"learn":[1.810700174],"iteration":413,"passed_time":0.7951884755,"remaining_time":1.125556634},
{"learn":[1.809989235],"iteration":414,"passed_time":0.7966198233,"remaining_time":1.122946016},
{"learn":[1.809468453],"iteration":415,"passed_time":0.7980659232,"remaining_time":1.120361777},
{"learn":[1.809088669],"iteration":416,"passed_time":0.7997145415,"remaining_time":1.118066134},
{"learn":[1.808600564],"iteration":417,"passed_time":0.8010873722,"remaining_time":1.115389595},
{"learn":[1.808132273],"iteration":418,"passed_time":0.8024757274,"remaining_time":1.112740806},
{"learn":[1.807384983],"iteration":419,"passed_time":0.8039905967,"remaining_time":1.110272729},
{"learn":[1.806925865],"iteration":420,"passed_time":0.805310433,"remaining_time":1.107540952},
{"learn":[1.806169311],"iteration":421,"passed_time":0.8068352622,"remaining_time":1.105096639},
{"learn":[1.805304175],"iteration":422,"passed_time":0.8083727658,"remaining_time":1.102673962},
{"learn":[1.804257451],"iteration":423,"passed_time":0.8099015518,"remaining_time":1.100243618},
{"learn":[1.803757996],"iteration":424,"passed_time":0.8112889256,"remaining_time":1.097626193},
{"learn":[1.803165966],"iteration":425,"passed_time":0.8126816135,"remaining_time":1.095021705},
{"learn":[1.802680653],"iteration":426,"passed_time":0.81426425,"remaining_time":1.092677787},
{"learn":[1.80204549],"iteration":427,"passed_time":0.8159898228,"remaining_time":1.090528455},
{"learn":[1.801102173],"iteration":428,"passed_time":0.8174206382,"remaining_time":1.087988775},
{"learn":[1.80067667],"iteration":429,"passed_time":0.818936468,"remaining_time":1.085566946},
{"learn":[1.800204928],"iteration":430,"passed_time":0.8203428116,"remaining_time":1.083004779},
{"learn":[1.799895338],"iteration":431,"passed_time":0.8218735499,"remaining_time":1.080611519},
{"learn":[1.799028818],"iteration":432,"passed_time":0.8233610144,"remaining_time":1.078165578},
{"learn":[1.79828401],"iteration":433,"passed_time":0.8249906734,"remaining_time":1.075909496},
{"learn":[1.797631012],"iteration":434,"passed_time":0.8266053716,"remaining_time":1.073636862},
{"learn":[1.797176607],"iteration":435,"passed_time":0.8280441738,"remaining_time":1.071139711},
{"learn":[1.796533626],"iteration":436,"passed_time":0.8294730682,"remaining_time":1.068634639},
{"learn":[1.796172217],"iteration":437,"passed_time":0.830887148,"remaining_time":1.066115473},
{"learn":[1.79552987],"iteration":438,"passed_time":0.8324091166,"remaining_time":1.063739213},
{"learn":[1.794926798],"iteration":439,"passed_time":0.8338262762,"remaining_time":1.061233442},
{"learn":[1.794073036],"iteration":440,"passed_time":0.8352256145,"remaining_time":1.058710019},
{"learn":[1.793481077],"iteration":441,"passed_time":0.8367542753,"remaining_time":1.056354945},
{"learn":[1.792762575],"iteration":442,"passed_time":0.838269938,"remaining_time":1.053987258},
{"learn":[1.792038458],"iteration":443,"passed_time":0.8397733335,"remaining_time":1.051608048},
{"learn":[1.791502748],"iteration":444,"passed_time":0.8425853206,"remaining_time":1.050864838},
{"learn":[1.790845576],"iteration":445,"passed_time":0.8443622487,"remaining_time":1.04882665},
{"learn":[1.790457019],"iteration":446,"passed_time":0.8457049281,"remaining_time":1.046252405},
{"learn":[1.789968724],"iteration":447,"passed_time":0.8470884391,"remaining_time":1.04373397},
{"learn":[1.78941926],"iteration":448,"passed_time":0.8485823445,"remaining_time":1.041356062},
{"learn":[1.788984968],"iteration":449,"passed_time":0.8500959192,"remaining_time":1.039006123},
{"learn":[1.788582374],"iteration":450,"passed_time":0.8522188242,"remaining_time":1.037401629},
{"learn":[1.787905825],"iteration":451,"passed_time":0.853738736,"remaining_time":1.035063777},
{"learn":[1.787388213],"iteration":452,"passed_time":0.8551306096,"remaining_time":1.03257493},
{"learn":[1.786807328],"iteration":453,"passed_time":0.8566362706,"remaining_time":1.030227762},
{"learn":[1.786173632],"iteration":454,"passed_time":0.8582998184,"remaining_time":1.028073409},
{"learn":[1.785581379],"iteration":455,"passed_time":0.8596928926,"remaining_time":1.025598539},
{"learn":[1.785105256],"iteration":456,"passed_time":0.8611172351,"remaining_time":1.023165555},
{"learn":[1.784603525],"iteration":457,"passed_time":0.8625287466,"remaining_time":1.020721792},
{"learn":[1.783975902],"iteration":458,"passed_time":0.8639256419,"remaining_time":1.018265299},
{"learn":[1.783282505],"iteration":459,"passed_time":0.8653785801,"remaining_time":1.015879203},
{"learn":[1.782862281],"iteration":460,"passed_time":0.8669797478,"remaining_time":1.013670464},
{"learn":[1.782410106],"iteration":461,"passed_time":0.8685355112,"remaining_time":1.011411483},
{"learn":[1.782052224],"iteration":462,"passed_time":0.8699841689,"remaining_time":1.009031315},
{"learn":[1.781596727],"iteration":463,"passed_time":0.8714220732,"remaining_time":1.00664274},
{"learn":[1.78100244],"iteration":464,"passed_time":0.8732111432,"remaining_time":1.004662283},
{"learn":[1.780260328],"iteration":465,"passed_time":0.8747112083,"remaining_time":1.00235147},
{"learn":[1.779821841],"iteration":466,"passed_time":0.8761535705,"remaining_time":0.9999782721},
{"learn":[1.779493518],"iteration":467,"passed_time":0.8775030987,"remaining_time":0.9975035225},
{"learn":[1.779016797],"iteration":468,"passed_time":0.8790045106,"remaining_time":0.9952055333},
{"learn":[1.778463213],"iteration":469,"passed_time":0.8805277007,"remaining_time":0.9929354922},
{"learn":[1.778058863],"iteration":470,"passed_time":0.8819843033,"remaining_time":0.9905938354},
{"learn":[1.777583229],"iteration":471,"passed_time":0.8838084523,"remaining_time":0.9886670822},
{"learn":[1.777073864],"iteration":472,"passed_time":0.8852529026,"remaining_time":0.986317716},
{"learn":[1.776709917],"iteration":473,"passed_time":0.8870909579,"remaining_time":0.9844089532},
{"learn":[1.776322211],"iteration":474,"passed_time":0.8886269789,"remaining_time":0.9821666609},
{"learn":[1.775932725],"iteration":475,"passed_time":0.8900252732,"remaining_time":0.9797757209},
{"learn":[1.775683501],"iteration":476,"passed_time":0.8914984339,"remaining_time":0.9774710293},
{"learn":[1.775192371],"iteration":477,"passed_time":0.8929450975,"remaining_time":0.9751408806},
{"learn":[1.77452147],"iteration":478,"passed_time":0.8944482529,"remaining_time":0.9728758659},
{"learn":[1.774106389],"iteration":479,"passed_time":0.8958713322,"remaining_time":0.9705272765},
{"learn":[1.773615402],"iteration":480,"passed_time":0.8975070986,"remaining_time":0.9684120254},
{"learn":[1.773077008],"iteration":481,"passed_time":0.8989748201,"remaining_time":0.9661181676},
{"learn":[1.77265044],"iteration":482,"passed_time":0.9004983651,"remaining_time":0.963887484},
{"learn":[1.772083832],"iteration":483,"passed_time":0.9019040406,"remaining_time":0.9615340598},
{"learn":[1.77162382],"iteration":484,"passed_time":0.9044071141,"remaining_time":0.9603498222},
{"learn":[1.771344127],"iteration":485,"passed_time":0.9058524518,"remaining_time":0.9580414819},
{"learn":[1.770919861],"iteration":486,"passed_time":0.9074528469,"remaining_time":0.9559000215},
{"learn":[1.770574495],"iteration":487,"passed_time":0.9093975591,"remaining_time":0.9541220292},
{"learn":[1.769917175],"iteration":488,"passed_time":0.9109578848,"remaining_time":0.9519416751},
{"learn":[1.769503053],"iteration":489,"passed_time":0.9123599376,"remaining_time":0.9495991187},
{"learn":[1.769094408],"iteration":490,"passed_time":0.9137912332,"remaining_time":0.9472907082},
{"learn":[1.768484387],"iteration":491,"passed_time":0.9165789267,"remaining_time":0.9463863715},
{"learn":[1.768193161],"iteration":492,"passed_time":0.9179866903,"remaining_time":0.9440552778},
{"learn":[1.767862514],"iteration":493,"passed_time":0.9193679879,"remaining_time":0.9417008135},
{"learn":[1.767405223],"iteration":494,"passed_time":0.9207291778,"remaining_time":0.9393297673},
{"learn":[1.767069408],"iteration":495,"passed_time":0.9229330471,"remaining_time":0.937819064},
{"learn":[1.766612389],"iteration":496,"passed_time":0.9245676241,"remaining_time":0.9357294062},
{"learn":[1.766085427],"iteration":497,"passed_time":0.9261858093,"remaining_time":0.9336250527},
{"learn":[1.765761163],"iteration":498,"passed_time":0.9276026244,"remaining_time":0.9313204706},
{"learn":[1.765285828],"iteration":499,"passed_time":0.929273449,"remaining_time":0.929273449},
{"learn":[1.764774952],"iteration":500,"passed_time":0.9309114288,"remaining_time":0.9271952155},
{"learn":[1.764362298],"iteration":501,"passed_time":0.9322863788,"remaining_time":0.9248578021},
{"learn":[1.763967436],"iteration":502,"passed_time":0.9339222497,"remaining_time":0.9227820241},
{"learn":[1.763360234],"iteration":503,"passed_time":0.935702362,"remaining_time":0.9208499436},
{"learn":[1.763037722],"iteration":504,"passed_time":0.9370949351,"remaining_time":0.9185385997},
{"learn":[1.76238075],"iteration":505,"passed_time":0.9384210564,"remaining_time":0.9161660116},
{"learn":[1.762026813],"iteration":506,"passed_time":0.9401760601,"remaining_time":0.914214591},
{"learn":[1.761449492],"iteration":507,"passed_time":0.9419415666,"remaining_time":0.9122741157},
{"learn":[1.760724902],"iteration":508,"passed_time":0.9436538596,"remaining_time":0.9102829962},
{"learn":[1.760294637],"iteration":509,"passed_time":0.9451383793,"remaining_time":0.9080741291},
{"learn":[1.759654139],"iteration":510,"passed_time":0.9468215754,"remaining_time":0.9060582199},
{"learn":[1.759322842],"iteration":511,"passed_time":0.9482441014,"remaining_time":0.9037951591},
{"learn":[1.758744316],"iteration":512,"passed_time":0.9502810942,"remaining_time":0.9021186995},
{"learn":[1.758410893],"iteration":513,"passed_time":0.9517056246,"remaining_time":0.8998617384},
{"learn":[1.758018302],"iteration":514,"passed_time":0.9531199237,"remaining_time":0.8975983747},
{"learn":[1.757366804],"iteration":515,"passed_time":0.9545595088,"remaining_time":0.8953620199},
{"learn":[1.756828307],"iteration":516,"passed_time":0.9561868501,"remaining_time":0.8933041559},
{"learn":[1.756324407],"iteration":517,"passed_time":0.9577304716,"remaining_time":0.8911700527},
{"learn":[1.756151948],"iteration":518,"passed_time":0.9597158638,"remaining_time":0.8894476503},
{"learn":[1.755656429],"iteration":519,"passed_time":0.9612399201,"remaining_time":0.8872983878},
{"learn":[1.754885455],"iteration":520,"passed_time":0.9627292631,"remaining_time":0.8851196104},
{"learn":[1.754525177],"iteration":521,"passed_time":0.964150745,"remaining_time":0.8828813335},
{"learn":[1.753910806],"iteration":522,"passed_time":0.9669101979,"remaining_time":0.8818664711},
{"learn":[1.753525409],"iteration":523,"passed_time":0.9684152638,"remaining_time":0.8797054686},
{"learn":[1.753097502],"iteration":524,"passed_time":0.9698586179,"remaining_time":0.8774911304},
{"learn":[1.752495118],"iteration":525,"passed_time":0.9720528501,"remaining_time":0.8759563706},
{"learn":[1.751956714],"iteration":526,"passed_time":0.9753900831,"remaining_time":0.8754449892},
{"learn":[1.751680504],"iteration":527,"passed_time":0.9782833268,"remaining_time":0.8745260042},
{"learn":[1.750891792],"iteration":528,"passed_time":0.9807223498,"remaining_time":0.8731951356},
{"learn":[1.750274686],"iteration":529,"passed_time":0.9831447312,"remaining_time":0.8718453276},
{"learn":[1.74977506],"iteration":530,"passed_time":0.98527081,"remaining_time":0.8702297738},
{"learn":[1.749274291],"iteration":531,"passed_time":0.9869205036,"remaining_time":0.868193225},
{"learn":[1.748838524],"iteration":532,"passed_time":0.9882985335,"remaining_time":0.8659201035},
{"learn":[1.748355887],"iteration":533,"passed_time":0.9896961074,"remaining_time":0.8636673896},
{"learn":[1.747939647],"iteration":534,"passed_time":0.9926759002,"remaining_time":0.8627930721},
{"learn":[1.747391826],"iteration":535,"passed_time":0.9941817595,"remaining_time":0.860634956},
{"learn":[1.746888118],"iteration":536,"passed_time":0.9956514124,"remaining_time":0.858448052},
{"learn":[1.746609748],"iteration":537,"passed_time":0.9970674237,"remaining_time":0.8562177504},
{"learn":[1.746212269],"iteration":538,"passed_time":0.9991237203,"remaining_time":0.8545380985},
{"learn":[1.74564346],"iteration":539,"passed_time":1.001278635,"remaining_time":0.8529410594},
{"learn":[1.745295664],"iteration":540,"passed_time":1.0027213,"remaining_time":0.8507376648},
{"learn":[1.744924045],"iteration":541,"passed_time":1.004024119,"remaining_time":0.8484189048},
{"learn":[1.744640569],"iteration":542,"passed_time":1.005450288,"remaining_time":0.8462077012},
{"learn":[1.743990922],"iteration":543,"passed_time":1.007222372,"remaining_time":0.8442893414},
{"learn":[1.743524071],"iteration":544,"passed_time":1.008834158,"remaining_time":0.8422376915},
{"learn":[1.742888174],"iteration":545,"passed_time":1.010612495,"remaining_time":0.8403261409},
{"learn":[1.742501396],"iteration":546,"passed_time":1.012082848,"remaining_time":0.8381600183},
{"learn":[1.741948101],"iteration":547,"passed_time":1.014317619,"remaining_time":0.8366269414},
{"learn":[1.741545143],"iteration":548,"passed_time":1.016317251,"remaining_time":0.8348981426},
{"learn":[1.741007289],"iteration":549,"passed_time":1.017935823,"remaining_time":0.8328565822},
{"learn":[1.740305799],"iteration":550,"passed_time":1.019555031,"remaining_time":0.8308170761},
{"learn":[1.739872449],"iteration":551,"passed_time":1.021168706,"remaining_time":0.828774602},
{"learn":[1.739389578],"iteration":552,"passed_time":1.02279753,"remaining_time":0.8267459238},
{"learn":[1.739001179],"iteration":553,"passed_time":1.024499284,"remaining_time":0.824777402},
{"learn":[1.738478864],"iteration":554,"passed_time":1.02610577,"remaining_time":0.8227334556},
{"learn":[1.738250041],"iteration":555,"passed_time":1.027694326,"remaining_time":0.8206767643},
{"learn":[1.73768878],"iteration":556,"passed_time":1.029266888,"remaining_time":0.8186090331},
{"learn":[1.737381478],"iteration":557,"passed_time":1.030651683,"remaining_time":0.8163943441},
{"learn":[1.736888405],"iteration":558,"passed_time":1.032143219,"remaining_time":0.8142668326},
{"learn":[1.736557535],"iteration":559,"passed_time":1.034199849,"remaining_time":0.812585596},
{"learn":[1.735861972],"iteration":560,"passed_time":1.036216045,"remaining_time":0.8108713796},
{"learn":[1.735416806],"iteration":561,"passed_time":1.037739204,"remaining_time":0.8087718353},
{"learn":[1.734943566],"iteration":562,"passed_time":1.039772595,"remaining_time":0.8070703802},
{"learn":[1.734277222],"iteration":563,"passed_time":1.042085481,"remaining_time":0.8055838113},
{"learn":[1.734012318],"iteration":564,"passed_time":1.04346088,"remaining_time":0.8033725357},
{"learn":[1.733551216],"iteration":565,"passed_time":1.044912722,"remaining_time":0.8012228289},
{"learn":[1.733104322],"iteration":566,"passed_time":1.046330675,"remaining_time":0.799049704},
{"learn":[1.732575587],"iteration":567,"passed_time":1.04794601,"remaining_time":0.7970293595},
{"learn":[1.732189169],"iteration":568,"passed_time":1.049685405,"remaining_time":0.7951044108},
{"learn":[1.731854123],"iteration":569,"passed_time":1.05108038,"remaining_time":0.7929202864},
{"learn":[1.731355228],"iteration":570,"passed_time":1.052639661,"remaining_time":0.7908623726},
{"learn":[1.730822174],"iteration":571,"passed_time":1.054370225,"remaining_time":0.7889343639},
{"learn":[1.730384058],"iteration":572,"passed_time":1.056768635,"remaining_time":0.7875047249},
{"learn":[1.729829247],"iteration":573,"passed_time":1.058337533,"remaining_time":0.7854560782},
{"learn":[1.729292998],"iteration":574,"passed_time":1.059817417,"remaining_time":0.7833433081},
{"learn":[1.728880619],"iteration":575,"passed_time":1.061210115,"remaining_time":0.781168557},
{"learn":[1.728516634],"iteration":576,"passed_time":1.062982439,"remaining_time":0.7792748211},
{"learn":[1.727964792],"iteration":577,"passed_time":1.064569513,"remaining_time":0.7772462532},
{"learn":[1.727582508],"iteration":578,"passed_time":1.066230889,"remaining_time":0.775273237},
{"learn":[1.7270966],"iteration":579,"passed_time":1.067704436,"remaining_time":0.7731652812},
{"learn":[1.726844034],"iteration":580,"passed_time":1.069050655,"remaining_time":0.7709676838},
{"learn":[1.726554817],"iteration":581,"passed_time":1.071363915,"remaining_time":0.7694675543},
{"learn":[1.72617593],"iteration":582,"passed_time":1.072749358,"remaining_time":0.7673009986},
{"learn":[1.725646804],"iteration":583,"passed_time":1.074216254,"remaining_time":0.7651951401},
{"learn":[1.725332395],"iteration":584,"passed_time":1.075664275,"remaining_time":0.7630780756},
{"learn":[1.724988125],"iteration":585,"passed_time":1.077153023,"remaining_time":0.7609920675},
{"learn":[1.724349731],"iteration":586,"passed_time":1.078598559,"remaining_time":0.7588776916},
{"learn":[1.724018531],"iteration":587,"passed_time":1.080094918,"remaining_time":0.7568012011},
{"learn":[1.723669376],"iteration":588,"passed_time":1.081436073,"remaining_time":0.7546183805},
{"learn":[1.723134839],"iteration":589,"passed_time":1.082902396,"remaining_time":0.7525253936},
{"learn":[1.722682691],"iteration":590,"passed_time":1.084437163,"remaining_time":0.7504818947},
{"learn":[1.722142021],"iteration":591,"passed_time":1.086319569,"remaining_time":0.748679703},
{"learn":[1.721720018],"iteration":592,"passed_time":1.087644103,"remaining_time":0.746494351},
{"learn":[1.721225345],"iteration":593,"passed_time":1.089072288,"remaining_time":0.7443827423},
{"learn":[1.720720708],"iteration":594,"passed_time":1.090689575,"remaining_time":0.7424021479},
{"learn":[1.719982205],"iteration":595,"passed_time":1.092215793,"remaining_time":0.7403610409},
{"learn":[1.719564555],"iteration":596,"passed_time":1.093703184,"remaining_time":0.738295449},
{"learn":[1.718872957],"iteration":597,"passed_time":1.095181293,"remaining_time":0.7362255516},
{"learn":[1.718521945],"iteration":598,"passed_time":1.096618686,"remaining_time":0.7341303724},
{"learn":[1.718095935],"iteration":599,"passed_time":1.098030135,"remaining_time":0.7320200899},
{"learn":[1.717619112],"iteration":600,"passed_time":1.099463007,"remaining_time":0.7299263557},
{"learn":[1.717277396],"iteration":601,"passed_time":1.100876774,"remaining_time":0.7278221858},
{"learn":[1.716798291],"iteration":602,"passed_time":1.102693312,"remaining_time":0.7259854805},
{"learn":[1.716417752],"iteration":603,"passed_time":1.104104426,"remaining_time":0.7238830346},
{"learn":[1.715943222],"iteration":604,"passed_time":1.105595429,"remaining_time":0.7218350325},
{"learn":[1.715595468],"iteration":605,"passed_time":1.107154795,"remaining_time":0.7198333154},
{"learn":[1.714973893],"iteration":606,"passed_time":1.108650652,"remaining_time":0.7177919381},
{"learn":[1.714676341],"iteration":607,"passed_time":1.110121328,"remaining_time":0.7157361196},
{"learn":[1.714252279],"iteration":608,"passed_time":1.111546725,"remaining_time":0.7136531521},
{"learn":[1.713753404],"iteration":609,"passed_time":1.112996114,"remaining_time":0.7115876794},
{"learn":[1.713464046],"iteration":610,"passed_time":1.114390483,"remaining_time":0.7094891944},
{"learn":[1.713006696],"iteration":611,"passed_time":1.115849748,"remaining_time":0.7074341537},
{"learn":[1.712524575],"iteration":612,"passed_time":1.118399697,"remaining_time":0.7060696295},
{"learn":[1.712165767],"iteration":613,"passed_time":1.119775274,"remaining_time":0.7039629572},
{"learn":[1.71178209],"iteration":614,"passed_time":1.121256703,"remaining_time":0.7019249281},
{"learn":[1.711320579],"iteration":615,"passed_time":1.122750306,"remaining_time":0.6998962946},
{"learn":[1.710884003],"iteration":616,"passed_time":1.124252041,"remaining_time":0.6978744438},
{"learn":[1.710407988],"iteration":617,"passed_time":1.125776829,"remaining_time":0.6958685253},
{"learn":[1.710129587],"iteration":618,"passed_time":1.12719118,"remaining_time":0.6937961868},
{"learn":[1.709891969],"iteration":619,"passed_time":1.128637677,"remaining_time":0.6917456728},
{"learn":[1.709572414],"iteration":620,"passed_time":1.130027097,"remaining_time":0.68966227},
{"learn":[1.709232102],"iteration":621,"passed_time":1.131442095,"remaining_time":0.6875966431},
{"learn":[1.708761581],"iteration":622,"passed_time":1.133072402,"remaining_time":0.6856633955},
{"learn":[1.708492751],"iteration":623,"passed_time":1.13446581,"remaining_time":0.6835883726},
{"learn":[1.707801143],"iteration":624,"passed_time":1.135856733,"remaining_time":0.68151404},
{"learn":[1.70747007],"iteration":625,"passed_time":1.13739171,"remaining_time":0.6795279548},
{"learn":[1.706667667],"iteration":626,"passed_time":1.138862668,"remaining_time":0.6775052237},
{"learn":[1.706200365],"iteration":627,"passed_time":1.140322601,"remaining_time":0.6754777193},
{"learn":[1.705673531],"iteration":628,"passed_time":1.14174637,"remaining_time":0.6734306886},
{"learn":[1.705139884],"iteration":629,"passed_time":1.143267357,"remaining_time":0.6714427334},
{"learn":[1.704657717],"iteration":630,"passed_time":1.144655587,"remaining_time":0.6693786236},
{"learn":[1.704193017],"iteration":631,"passed_time":1.146065094,"remaining_time":0.667329042},
{"learn":[1.703749371],"iteration":632,"passed_time":1.147587198,"remaining_time":0.6653467641},
{"learn":[1.703308306],"iteration":633,"passed_time":1.149149748,"remaining_time":0.6633892865},
{"learn":[1.70299843],"iteration":634,"passed_time":1.150538239,"remaining_time":0.6613330033},
{"learn":[1.702676105],"iteration":635,"passed_time":1.151969064,"remaining_time":0.6593030495},
{"learn":[1.701961059],"iteration":636,"passed_time":1.153497892,"remaining_time":0.657330824},
{"learn":[1.701512353],"iteration":637,"passed_time":1.154995525,"remaining_time":0.6553422883},
{"learn":[1.700880827],"iteration":638,"passed_time":1.156435789,"remaining_time":0.653322879},
{"learn":[1.700477709],"iteration":639,"passed_time":1.157891629,"remaining_time":0.6513140413},
{"learn":[1.700129852],"iteration":640,"passed_time":1.159265974,"remaining_time":0.6492612863},
{"learn":[1.699544244],"iteration":641,"passed_time":1.160731252,"remaining_time":0.6472613523},
{"learn":[1.699287624],"iteration":642,"passed_time":1.162191039,"remaining_time":0.6452600325},
{"learn":[1.69892913],"iteration":643,"passed_time":1.163843415,"remaining_time":0.6433668567},
{"learn":[1.698485384],"iteration":644,"passed_time":1.165380355,"remaining_time":0.6414108929},
{"learn":[1.698122768],"iteration":645,"passed_time":1.166815012,"remaining_time":0.6394001769},
{"learn":[1.697817354],"iteration":646,"passed_time":1.168253115,"remaining_time":0.6373931214},
{"learn":[1.697458011],"iteration":647,"passed_time":1.169745642,"remaining_time":0.6354173858},
{"learn":[1.697136091],"iteration":648,"passed_time":1.171230736,"remaining_time":0.6334391191},
{"learn":[1.696560618],"iteration":649,"passed_time":1.172708073,"remaining_time":0.631458193},
{"learn":[1.696101617],"iteration":650,"passed_time":1.174080851,"remaining_time":0.6294227605},
{"learn":[1.69547794],"iteration":651,"passed_time":1.175582535,"remaining_time":0.6274581626},
{"learn":[1.695056209],"iteration":652,"passed_time":1.176970138,"remaining_time":0.6254343613},
{"learn":[1.694611329],"iteration":653,"passed_time":1.178475068,"remaining_time":0.6234745774},
{"learn":[1.694096691],"iteration":654,"passed_time":1.179862891,"remaining_time":0.6214544999},
{"learn":[1.69379934],"iteration":655,"passed_time":1.181304596,"remaining_time":0.619464605},
{"learn":[1.693420949],"iteration":656,"passed_time":1.182829519,"remaining_time":0.6175198249},
{"learn":[1.69309599],"iteration":657,"passed_time":1.184287364,"remaining_time":0.6155414566},
{"learn":[1.692769512],"iteration":658,"passed_time":1.185729267,"remaining_time":0.6135564187},
{"learn":[1.692542952],"iteration":659,"passed_time":1.187129503,"remaining_time":0.6115515621},
{"learn":[1.69205564],"iteration":660,"passed_time":1.188540106,"remaining_time":0.6095538517},
{"learn":[1.691651591],"iteration":661,"passed_time":1.190082506,"remaining_time":0.607625207},
{"learn":[1.691255512],"iteration":662,"passed_time":1.191558141,"remaining_time":0.6056637912},
{"learn":[1.690851931],"iteration":663,"passed_time":1.193006935,"remaining_time":0.603690256},
{"learn":[1.690372946],"iteration":664,"passed_time":1.194545545,"remaining_time":0.6017635451},
{"learn":[1.689931887],"iteration":665,"passed_time":1.196061531,"remaining_time":0.5998266537},
{"learn":[1.689685199],"iteration":666,"passed_time":1.197581568,"remaining_time":0.5978930468},
{"learn":[1.689302037],"iteration":667,"passed_time":1.198969443,"remaining_time":0.5958949928},
{"learn":[1.688902956],"iteration":668,"passed_time":1.200429449,"remaining_time":0.593934451},
{"learn":[1.688496684],"iteration":669,"passed_time":1.201928878,"remaining_time":0.5919948203},
{"learn":[1.687962371],"iteration":670,"passed_time":1.203354504,"remaining_time":0.5900203158},
{"learn":[1.687278685],"iteration":671,"passed_time":1.20475877,"remaining_time":0.5880370189},
{"learn":[1.686918069],"iteration":672,"passed_time":1.20623689,"remaining_time":0.586091327},
{"learn":[1.686652404],"iteration":673,"passed_time":1.207754067,"remaining_time":0.5841659136},
{"learn":[1.686283693],"iteration":674,"passed_time":1.209259832,"remaining_time":0.5822362155},
{"learn":[1.685884118],"iteration":675,"passed_time":1.210802107,"remaining_time":0.5803252701},
{"learn":[1.685597117],"iteration":676,"passed_time":1.212317582,"remaining_time":0.5784026276},
{"learn":[1.685204294],"iteration":677,"passed_time":1.213768567,"remaining_time":0.5764505586},
{"learn":[1.684723702],"iteration":678,"passed_time":1.215297082,"remaining_time":0.5745366176},
{"learn":[1.684253108],"iteration":679,"passed_time":1.216661488,"remaining_time":0.5725465824},
{"learn":[1.683896194],"iteration":680,"passed_time":1.218113256,"remaining_time":0.570599308},
{"learn":[1.683568009],"iteration":681,"passed_time":1.219617456,"remaining_time":0.5686779339},
{"learn":[1.682943026],"iteration":682,"passed_time":1.22111087,"remaining_time":0.5667527759},
{"learn":[1.682576389],"iteration":683,"passed_time":1.222615268,"remaining_time":0.5648339543},
{"learn":[1.682102537],"iteration":684,"passed_time":1.224173245,"remaining_time":0.5629409813},
{"learn":[1.681725112],"iteration":685,"passed_time":1.225602547,"remaining_time":0.5609900869},
{"learn":[1.681419167],"iteration":686,"passed_time":1.227080144,"remaining_time":0.559062715},
{"learn":[1.680667783],"iteration":687,"passed_time":1.228655535,"remaining_time":0.5571809986},
{"learn":[1.680185837],"iteration":688,"passed_time":1.230080609,"remaining_time":0.5552323212},
{"learn":[1.679932766],"iteration":689,"passed_time":1.231413631,"remaining_time":0.5532438052},
{"learn":[1.679594552],"iteration":690,"passed_time":1.232856912,"remaining_time":0.5513064917},
{"learn":[1.679282218],"iteration":691,"passed_time":1.234292478,"remaining_time":0.5493671721},
{"learn":[1.678660221],"iteration":692,"passed_time":1.235691492,"remaining_time":0.5474131142},
{"learn":[1.678245049],"iteration":693,"passed_time":1.237103923,"remaining_time":0.545466571},
{"learn":[1.67793461],"iteration":694,"passed_time":1.238768338,"remaining_time":0.5436321481},
{"learn":[1.677482492],"iteration":695,"passed_time":1.240321376,"remaining_time":0.5417495666},
{"learn":[1.676835916],"iteration":696,"passed_time":1.241729578,"remaining_time":0.5398049672},
{"learn":[1.6764745],"iteration":697,"passed_time":1.243137237,"remaining_time":0.53786167},
{"learn":[1.676125679],"iteration":698,"passed_time":1.244586991,"remaining_time":0.5359380319},
{"learn":[1.675625399],"iteration":699,"passed_time":1.246297165,"remaining_time":0.5341273563},
{"learn":[1.675236624],"iteration":700,"passed_time":1.247691857,"remaining_time":0.5321824041},
{"learn":[1.674827497],"iteration":701,"passed_time":1.249100383,"remaining_time":0.5302448918},
{"learn":[1.674448836],"iteration":702,"passed_time":1.250572019,"remaining_time":0.5283355472},
{"learn":[1.673679931],"iteration":703,"passed_time":1.252060694,"remaining_time":0.52643461},
{"learn":[1.673362089],"iteration":704,"passed_time":1.25373439,"remaining_time":0.5246122624},
{"learn":[1.673067952],"iteration":705,"passed_time":1.255075065,"remaining_time":0.5226516558},
{"learn":[1.672531248],"iteration":706,"passed_time":1.256605051,"remaining_time":0.5207712586},
{"learn":[1.672196538],"iteration":707,"passed_time":1.258142304,"remaining_time":0.5188948484},
{"learn":[1.671781872],"iteration":708,"passed_time":1.259676268,"remaining_time":0.5170180451},
{"learn":[1.671344785],"iteration":709,"passed_time":1.261069989,"remaining_time":0.5150849252},
{"learn":[1.671006027],"iteration":710,"passed_time":1.262766017,"remaining_time":0.5132762008},
{"learn":[1.670478796],"iteration":711,"passed_time":1.264222765,"remaining_time":0.5113710062},
{"learn":[1.670193087],"iteration":712,"passed_time":1.265601171,"remaining_time":0.5094355345},
{"learn":[1.669803501],"iteration":713,"passed_time":1.26733068,"remaining_time":0.5076422611},
{"learn":[1.669178721],"iteration":714,"passed_time":1.268782584,"remaining_time":0.5057385127},
{"learn":[1.668749417],"iteration":715,"passed_time":1.270232077,"remaining_time":0.5038350698},
{"learn":[1.668403681],"iteration":716,"passed_time":1.271730524,"remaining_time":0.5019522153},
{"learn":[1.668024941],"iteration":717,"passed_time":1.273192608,"remaining_time":0.5000561496},
{"learn":[1.667610465],"iteration":718,"passed_time":1.274809937,"remaining_time":0.4982219643},
{"learn":[1.66695342],"iteration":719,"passed_time":1.276324096,"remaining_time":0.4963482597},
{"learn":[1.6666063],"iteration":720,"passed_time":1.277704632,"remaining_time":0.4944238451},
{"learn":[1.666295207],"iteration":721,"passed_time":1.279062283,"remaining_time":0.4924921254},
{"learn":[1.666122681],"iteration":722,"passed_time":1.280450669,"remaining_time":0.4905737695},
{"learn":[1.665669138],"iteration":723,"passed_time":1.282104372,"remaining_time":0.4887580202},
{"learn":[1.66504754],"iteration":724,"passed_time":1.283645039,"remaining_time":0.4868998423},
{"learn":[1.664712339],"iteration":725,"passed_time":1.285028873,"remaining_time":0.4849833489},
{"learn":[1.664283986],"iteration":726,"passed_time":1.28649268,"remaining_time":0.4830983516},
{"learn":[1.664116826],"iteration":727,"passed_time":1.288050918,"remaining_time":0.4812497934},
{"learn":[1.663666156],"iteration":728,"passed_time":1.289381925,"remaining_time":0.4793175606},
{"learn":[1.663147643],"iteration":729,"passed_time":1.29096715,"remaining_time":0.4774810009},
{"learn":[1.662789689],"iteration":730,"passed_time":1.292356915,"remaining_time":0.4755732013},
{"learn":[1.66242236],"iteration":731,"passed_time":1.293835233,"remaining_time":0.4736992384},
{"learn":[1.662111952],"iteration":732,"passed_time":1.295318907,"remaining_time":0.4718283059},
{"learn":[1.661568645],"iteration":733,"passed_time":1.296848957,"remaining_time":0.469975235},
{"learn":[1.661243479],"iteration":734,"passed_time":1.2982674,"remaining_time":0.4680828042},
{"learn":[1.66086076],"iteration":735,"passed_time":1.2996912,"remaining_time":0.4661935826},
{"learn":[1.660546375],"iteration":736,"passed_time":1.301282481,"remaining_time":0.4643653901},
{"learn":[1.660026878],"iteration":737,"passed_time":1.30359096,"remaining_time":0.4627924546},
{"learn":[1.659413321],"iteration":738,"passed_time":1.305522862,"remaining_time":0.4610845291},
{"learn":[1.65897627],"iteration":739,"passed_time":1.307178768,"remaining_time":0.4592790265},
{"learn":[1.65853001],"iteration":740,"passed_time":1.309449255,"remaining_time":0.4576887409},
{"learn":[1.658067074],"iteration":741,"passed_time":1.312846185,"remaining_time":0.4564882963},
{"learn":[1.657761374],"iteration":742,"passed_time":1.314317582,"remaining_time":0.4546159065},
{"learn":[1.657353818],"iteration":743,"passed_time":1.315817229,"remaining_time":0.4527543155},
{"learn":[1.656917226],"iteration":744,"passed_time":1.317704468,"remaining_time":0.4510263616},
{"learn":[1.656593608],"iteration":745,"passed_time":1.319338919,"remaining_time":0.4492119109},
{"learn":[1.656339869],"iteration":746,"passed_time":1.320809063,"remaining_time":0.447342293},
{"learn":[1.655893278],"iteration":747,"passed_time":1.322338956,"remaining_time":0.4454938727},
{"learn":[1.655466117],"iteration":748,"passed_time":1.324000885,"remaining_time":0.4436905503},
{"learn":[1.654970771],"iteration":749,"passed_time":1.327389849,"remaining_time":0.442463283},
{"learn":[1.654475131],"iteration":750,"passed_time":1.328891251,"remaining_time":0.4406044226},
{"learn":[1.654209901],"iteration":751,"passed_time":1.330303535,"remaining_time":0.4387171231},
{"learn":[1.653626579],"iteration":752,"passed_time":1.332012946,"remaining_time":0.4369285494},
{"learn":[1.653180166],"iteration":753,"passed_time":1.333902618,"remaining_time":0.4351989972},
{"learn":[1.652866899],"iteration":754,"passed_time":1.335501541,"remaining_time":0.4333746721},
{"learn":[1.652595043],"iteration":755,"passed_time":1.336968615,"remaining_time":0.4315083889},
{"learn":[1.652238631],"iteration":756,"passed_time":1.339097387,"remaining_time":0.4298555681},
{"learn":[1.651963061],"iteration":757,"passed_time":1.340620285,"remaining_time":0.4280080593},
{"learn":[1.651734045],"iteration":758,"passed_time":1.343376939,"remaining_time":0.4265531519},
{"learn":[1.651315901],"iteration":759,"passed_time":1.345178652,"remaining_time":0.4247932586},
{"learn":[1.650953362],"iteration":760,"passed_time":1.346817613,"remaining_time":0.4229821414},
{"learn":[1.650594255],"iteration":761,"passed_time":1.348515541,"remaining_time":0.4211898933},
{"learn":[1.650163387],"iteration":762,"passed_time":1.34994977,"remaining_time":0.4193159836},
{"learn":[1.649581007],"iteration":763,"passed_time":1.351600184,"remaining_time":0.4175100045},
{"learn":[1.649275333],"iteration":764,"passed_time":1.353506977,"remaining_time":0.4157831891},
{"learn":[1.649019908],"iteration":765,"passed_time":1.357031006,"remaining_time":0.4145499418},
{"learn":[1.648381943],"iteration":766,"passed_time":1.361052404,"remaining_time":0.4134618125},
{"learn":[1.648061093],"iteration":767,"passed_time":1.365426722,"remaining_time":0.4124726557},
{"learn":[1.647733775],"iteration":768,"passed_time":1.36759497,"remaining_time":0.410812013},
{"learn":[1.647437677],"iteration":769,"passed_time":1.369336965,"remaining_time":0.4090227298},
{"learn":[1.647096859],"iteration":770,"passed_time":1.370859842,"remaining_time":0.4071684874},
{"learn":[1.646726599],"iteration":771,"passed_time":1.372324316,"remaining_time":0.4052978551},
{"learn":[1.646326739],"iteration":772,"passed_time":1.374021596,"remaining_time":0.4034966396},
{"learn":[1.645848802],"iteration":773,"passed_time":1.375721121,"remaining_time":0.401696348},
{"learn":[1.645521164],"iteration":774,"passed_time":1.378793121,"remaining_time":0.400294777},
{"learn":[1.645244023],"iteration":775,"passed_time":1.380421219,"remaining_time":0.3984721045},
{"learn":[1.644800635],"iteration":776,"passed_time":1.381987861,"remaining_time":0.3966322948},
{"learn":[1.64438966],"iteration":777,"passed_time":1.383426559,"remaining_time":0.3947566788},
{"learn":[1.644088294],"iteration":778,"passed_time":1.386319776,"remaining_time":0.3932948274},
{"learn":[1.64357968],"iteration":779,"passed_time":1.387994151,"remaining_time":0.3914855296},
{"learn":[1.643114363],"iteration":780,"passed_time":1.389468501,"remaining_time":0.3896204889},
{"learn":[1.642869866],"iteration":781,"passed_time":1.390893303,"remaining_time":0.3877426344},
{"learn":[1.642575057],"iteration":782,"passed_time":1.392309221,"remaining_time":0.3858634749},
{"learn":[1.64230729],"iteration":783,"passed_time":1.393902496,"remaining_time":0.384034361},
{"learn":[1.641855463],"iteration":784,"passed_time":1.396842302,"remaining_time":0.3825746434},
{"learn":[1.641493823],"iteration":785,"passed_time":1.398359322,"remaining_time":0.380723785},
{"learn":[1.641052246],"iteration":786,"passed_time":1.400197534,"remaining_time":0.378960705},
{"learn":[1.640706991],"iteration":787,"passed_time":1.402735552,"remaining_time":0.3773857068},
{"learn":[1.64032484],"iteration":788,"passed_time":1.404371673,"remaining_time":0.3755670761},
{"learn":[1.639958396],"iteration":789,"passed_time":1.40606342,"remaining_time":0.3737636939},
{"learn":[1.639538412],"iteration":790,"passed_time":1.407612543,"remaining_time":0.3719229097},
{"learn":[1.639122361],"iteration":791,"passed_time":1.409880452,"remaining_time":0.3702716338},
{"learn":[1.638811482],"iteration":792,"passed_time":1.411289604,"remaining_time":0.3683946381},
{"learn":[1.638483875],"iteration":793,"passed_time":1.4126704,"remaining_time":0.3665114641},
{"learn":[1.638079649],"iteration":794,"passed_time":1.414161351,"remaining_time":0.3646579585},
{"learn":[1.637815152],"iteration":795,"passed_time":1.415941077,"remaining_time":0.3628793716},
{"learn":[1.637583167],"iteration":796,"passed_time":1.41770577,"remaining_time":0.3610969526},
{"learn":[1.637334932],"iteration":797,"passed_time":1.419041736,"remaining_time":0.3592060535},
{"learn":[1.636805802],"iteration":798,"passed_time":1.420467551,"remaining_time":0.357339146},
{"learn":[1.636300007],"iteration":799,"passed_time":1.422106783,"remaining_time":0.3555266958},
{"learn":[1.636015311],"iteration":800,"passed_time":1.423648379,"remaining_time":0.3536904213},
{"learn":[1.635890182],"iteration":801,"passed_time":1.425146659,"remaining_time":0.3518441877},
{"learn":[1.63561503],"iteration":802,"passed_time":1.426621908,"remaining_time":0.3499931704},
{"learn":[1.635233417],"iteration":803,"passed_time":1.428049257,"remaining_time":0.3481314109},
{"learn":[1.634854916],"iteration":804,"passed_time":1.429949003,"remaining_time":0.3463851623},
{"learn":[1.634351712],"iteration":805,"passed_time":1.431531922,"remaining_time":0.344562274},
{"learn":[1.633872248],"iteration":806,"passed_time":1.433086798,"remaining_time":0.3427332738},
{"learn":[1.633658021],"iteration":807,"passed_time":1.43452157,"remaining_time":0.3408764127},
{"learn":[1.633372772],"iteration":808,"passed_time":1.435944701,"remaining_time":0.3390178467},
{"learn":[1.632971157],"iteration":809,"passed_time":1.437621863,"remaining_time":0.3372199432},
{"learn":[1.632722433],"iteration":810,"passed_time":1.439053389,"remaining_time":0.335365093},
{"learn":[1.632299399],"iteration":811,"passed_time":1.440630147,"remaining_time":0.3335449109},
{"learn":[1.631894823],"iteration":812,"passed_time":1.442189356,"remaining_time":0.3317212909},
{"learn":[1.631591467],"iteration":813,"passed_time":1.444305882,"remaining_time":0.3300256683},
{"learn":[1.631377875],"iteration":814,"passed_time":1.445705335,"remaining_time":0.3281662417},
{"learn":[1.631092131],"iteration":815,"passed_time":1.447127746,"remaining_time":0.3263131192},
{"learn":[1.630653168],"iteration":816,"passed_time":1.44860455,"remaining_time":0.3244732347},
{"learn":[1.630198274],"iteration":817,"passed_time":1.450461931,"remaining_time":0.3227189136},
{"learn":[1.629817956],"iteration":818,"passed_time":1.451916142,"remaining_time":0.3208752403},
{"learn":[1.629511058],"iteration":819,"passed_time":1.453350643,"remaining_time":0.31902819},
{"learn":[1.629183101],"iteration":820,"passed_time":1.454735647,"remaining_time":0.317171353},
{"learn":[1.628885652],"iteration":821,"passed_time":1.456269089,"remaining_time":0.3153478077},
{"learn":[1.628668541],"iteration":822,"passed_time":1.458107729,"remaining_time":0.3135906052},
{"learn":[1.628449437],"iteration":823,"passed_time":1.459569302,"remaining_time":0.3117526663},
{"learn":[1.628174616],"iteration":824,"passed_time":1.461046952,"remaining_time":0.3099190503},
{"learn":[1.627795728],"iteration":825,"passed_time":1.462405375,"remaining_time":0.3080611806},
{"learn":[1.627254599],"iteration":826,"passed_time":1.46390259,"remaining_time":0.3062335526},
{"learn":[1.626702532],"iteration":827,"passed_time":1.465606384,"remaining_time":0.3044496354},
{"learn":[1.62645514],"iteration":828,"passed_time":1.467080297,"remaining_time":0.3026184931},
{"learn":[1.626130121],"iteration":829,"passed_time":1.468612173,"remaining_time":0.3008000837},
{"learn":[1.625649702],"iteration":830,"passed_time":1.470138694,"remaining_time":0.2989812746},
{"learn":[1.625457089],"iteration":831,"passed_time":1.472046688,"remaining_time":0.2972401965},
{"learn":[1.625081099],"iteration":832,"passed_time":1.4733892,"remaining_time":0.2953853498},
{"learn":[1.624725395],"iteration":833,"passed_time":1.474834632,"remaining_time":0.2935522169},
{"learn":[1.624303067],"iteration":834,"passed_time":1.476345471,"remaining_time":0.2917329374},
{"learn":[1.623971055],"iteration":835,"passed_time":1.477769981,"remaining_time":0.2898974603},
{"learn":[1.623735642],"iteration":836,"passed_time":1.479252986,"remaining_time":0.288074357},
{"learn":[1.623218765],"iteration":837,"passed_time":1.480770048,"remaining_time":0.2862586489},
{"learn":[1.622804975],"iteration":838,"passed_time":1.482195174,"remaining_time":0.2844260107},
{"learn":[1.622605064],"iteration":839,"passed_time":1.483768424,"remaining_time":0.282622557},
{"learn":[1.622372677],"iteration":840,"passed_time":1.485148688,"remaining_time":0.2807831646},
{"learn":[1.621786322],"iteration":841,"passed_time":1.486612464,"remaining_time":0.2789605335},
{"learn":[1.621169482],"iteration":842,"passed_time":1.488201907,"remaining_time":0.2771621582},
{"learn":[1.620926942],"iteration":843,"passed_time":1.489657633,"remaining_time":0.2753395624},
{"learn":[1.620420888],"iteration":844,"passed_time":1.491170215,"remaining_time":0.2735282644},
{"learn":[1.620105895],"iteration":845,"passed_time":1.492583658,"remaining_time":0.2716996258},
{"learn":[1.619932877],"iteration":846,"passed_time":1.494106681,"remaining_time":0.2698917618},
{"learn":[1.619522596],"iteration":847,"passed_time":1.495535774,"remaining_time":0.2680677331},
{"learn":[1.61923374],"iteration":848,"passed_time":1.496953811,"remaining_time":0.2662426684},
{"learn":[1.618786518],"iteration":849,"passed_time":1.498457457,"remaining_time":0.2644336689},
{"learn":[1.618401273],"iteration":850,"passed_time":1.499811381,"remaining_time":0.2625991724},
{"learn":[1.618071374],"iteration":851,"passed_time":1.501249608,"remaining_time":0.2607804484},
{"learn":[1.617788638],"iteration":852,"passed_time":1.502707453,"remaining_time":0.2589659973},
{"learn":[1.617157851],"iteration":853,"passed_time":1.504214649,"remaining_time":0.2571608182},
{"learn":[1.616705021],"iteration":854,"passed_time":1.505626338,"remaining_time":0.2553401392},
{"learn":[1.616562099],"iteration":855,"passed_time":1.506944984,"remaining_time":0.2535047637},
{"learn":[1.616014838],"iteration":856,"passed_time":1.508444131,"remaining_time":0.2517007126},
{"learn":[1.615769362],"iteration":857,"passed_time":1.509840149,"remaining_time":0.2498803044},
{"learn":[1.615424429],"iteration":858,"passed_time":1.511238318,"remaining_time":0.2480612373},
{"learn":[1.614870437],"iteration":859,"passed_time":1.51276014,"remaining_time":0.2462632787},
{"learn":[1.614571134],"iteration":860,"passed_time":1.51423303,"remaining_time":0.2444580617},
{"learn":[1.614199528],"iteration":861,"passed_time":1.515649177,"remaining_time":0.2426445318},
{"learn":[1.613747475],"iteration":862,"passed_time":1.517138217,"remaining_time":0.2408434945},
{"learn":[1.613451742],"iteration":863,"passed_time":1.518772741,"remaining_time":0.2390660796},
{"learn":[1.613028115],"iteration":864,"passed_time":1.520124859,"remaining_time":0.2372449201},
{"learn":[1.612670921],"iteration":865,"passed_time":1.521552605,"remaining_time":0.2354365462},
{"learn":[1.612371677],"iteration":866,"passed_time":1.522971247,"remaining_time":0.2336276538},
{"learn":[1.61216632],"iteration":867,"passed_time":1.524448197,"remaining_time":0.2318285277},
{"learn":[1.611695046],"iteration":868,"passed_time":1.525980512,"remaining_time":0.2300384892},
{"learn":[1.611394414],"iteration":869,"passed_time":1.527545922,"remaining_time":0.2282539884},
{"learn":[1.610994493],"iteration":870,"passed_time":1.529046916,"remaining_time":0.2264604503},
{"learn":[1.610727175],"iteration":871,"passed_time":1.530521153,"remaining_time":0.2246636554},
{"learn":[1.610289181],"iteration":872,"passed_time":1.531970948,"remaining_time":0.222864044},
{"learn":[1.609852658],"iteration":873,"passed_time":1.533412068,"remaining_time":0.2210639823},
{"learn":[1.609478751],"iteration":874,"passed_time":1.53485299,"remaining_time":0.2192647128},
{"learn":[1.609115757],"iteration":875,"passed_time":1.536225632,"remaining_time":0.2174565964},
{"learn":[1.608809271],"iteration":876,"passed_time":1.537610897,"remaining_time":0.2156512433},
{"learn":[1.608364436],"iteration":877,"passed_time":1.53908127,"remaining_time":0.2138586731},
{"learn":[1.608005509],"iteration":878,"passed_time":1.540554275,"remaining_time":0.2120671982},
{"learn":[1.607727851],"iteration":879,"passed_time":1.541933014,"remaining_time":0.2102635929},
{"learn":[1.607527842],"iteration":880,"passed_time":1.543404254,"remaining_time":0.2084734464},
{"learn":[1.607209261],"iteration":881,"passed_time":1.544881236,"remaining_time":0.2066847912},
{"learn":[1.606867134],"iteration":882,"passed_time":1.54633527,"remaining_time":0.2048938014},
{"learn":[1.606357228],"iteration":883,"passed_time":1.547726789,"remaining_time":0.2030953705},
{"learn":[1.605974361],"iteration":884,"passed_time":1.549173014,"remaining_time":0.2013049679},
{"learn":[1.605762799],"iteration":885,"passed_time":1.55047196,"remaining_time":0.1994963921},
{"learn":[1.605586281],"iteration":886,"passed_time":1.551875547,"remaining_time":0.1977022963},
{"learn":[1.605191209],"iteration":887,"passed_time":1.553319361,"remaining_time":0.1959141536},
{"learn":[1.604733419],"iteration":888,"passed_time":1.55488237,"remaining_time":0.1941416682},
{"learn":[1.604285632],"iteration":889,"passed_time":1.556261788,"remaining_time":0.1923469626},
{"learn":[1.603608449],"iteration":890,"passed_time":1.557800294,"remaining_time":0.190572651},
{"learn":[1.603243573],"iteration":891,"passed_time":1.559286484,"remaining_time":0.1887925339},
{"learn":[1.602967275],"iteration":892,"passed_time":1.560842373,"remaining_time":0.1870214265},
{"learn":[1.602643316],"iteration":893,"passed_time":1.562173255,"remaining_time":0.1852241219},
{"learn":[1.602341296],"iteration":894,"passed_time":1.563612527,"remaining_time":0.1834405757},
{"learn":[1.602079229],"iteration":895,"passed_time":1.565365505,"remaining_time":0.1816942104},
{"learn":[1.601865541],"iteration":896,"passed_time":1.566745341,"remaining_time":0.1799049834},
{"learn":[1.6013841],"iteration":897,"passed_time":1.568255126,"remaining_time":0.1781314285},
{"learn":[1.600864946],"iteration":898,"passed_time":1.569747037,"remaining_time":0.1763564525},
{"learn":[1.600441717],"iteration":899,"passed_time":1.571258138,"remaining_time":0.1745842375},
{"learn":[1.600159924],"iteration":900,"passed_time":1.572707505,"remaining_time":0.1728058191},
{"learn":[1.599856179],"iteration":901,"passed_time":1.574173754,"remaining_time":0.1710299645},
{"learn":[1.599580719],"iteration":902,"passed_time":1.57561241,"remaining_time":0.1692518315},
{"learn":[1.599290443],"iteration":903,"passed_time":1.577124022,"remaining_time":0.1674821971},
{"learn":[1.598800552],"iteration":904,"passed_time":1.578488083,"remaining_time":0.1656976441},
{"learn":[1.598412523],"iteration":905,"passed_time":1.580242231,"remaining_time":0.163954492},
{"learn":[1.598293823],"iteration":906,"passed_time":1.581703208,"remaining_time":0.1621812551},
{"learn":[1.598016293],"iteration":907,"passed_time":1.583170188,"remaining_time":0.1604093142},
{"learn":[1.597870123],"iteration":908,"passed_time":1.584576929,"remaining_time":0.1586320138},
{"learn":[1.597583552],"iteration":909,"passed_time":1.586024636,"remaining_time":0.1568595794},
{"learn":[1.597197419],"iteration":910,"passed_time":1.587577497,"remaining_time":0.1550981309},
{"learn":[1.596940591],"iteration":911,"passed_time":1.589058843,"remaining_time":0.1533302392},
{"learn":[1.59667688],"iteration":912,"passed_time":1.590533612,"remaining_time":0.1515623485},
{"learn":[1.596414947],"iteration":913,"passed_time":1.592064214,"remaining_time":0.1498003528},
{"learn":[1.596019061],"iteration":914,"passed_time":1.593525807,"remaining_time":0.148032452},
{"learn":[1.595679893],"iteration":915,"passed_time":1.595077457,"remaining_time":0.1462734786},
{"learn":[1.595471552],"iteration":916,"passed_time":1.59643065,"remaining_time":0.1444969945},
{"learn":[1.595169146],"iteration":917,"passed_time":1.597826491,"remaining_time":0.1427252421},
{"learn":[1.594821544],"iteration":918,"passed_time":1.599309904,"remaining_time":0.1409620263},
{"learn":[1.594493707],"iteration":919,"passed_time":1.600720444,"remaining_time":0.1391930821},
{"learn":[1.594143975],"iteration":920,"passed_time":1.602171086,"remaining_time":0.1374283559},
{"learn":[1.593704889],"iteration":921,"passed_time":1.603755695,"remaining_time":0.1356756445},
{"learn":[1.593230858],"iteration":922,"passed_time":1.605264217,"remaining_time":0.1339169498},
{"learn":[1.593048125],"iteration":923,"passed_time":1.606796636,"remaining_time":0.1321607623},
{"learn":[1.592884995],"iteration":924,"passed_time":1.608220488,"remaining_time":0.1303962558},
{"learn":[1.592541158],"iteration":925,"passed_time":1.609709403,"remaining_time":0.1286376845},
{"learn":[1.592123522],"iteration":926,"passed_time":1.611256293,"remaining_time":0.1268842604},
{"learn":[1.59158517],"iteration":927,"passed_time":1.612782229,"remaining_time":0.1251296557},
{"learn":[1.591382542],"iteration":928,"passed_time":1.614255745,"remaining_time":0.123371537},
{"learn":[1.591131633],"iteration":929,"passed_time":1.615665815,"remaining_time":0.1216092549},
{"learn":[1.590765752],"iteration":930,"passed_time":1.617066688,"remaining_time":0.1198470478},
{"learn":[1.590465954],"iteration":931,"passed_time":1.618494027,"remaining_time":0.118087547},
{"learn":[1.590096196],"iteration":932,"passed_time":1.61992289,"remaining_time":0.1163288678},
{"learn":[1.589818397],"iteration":933,"passed_time":1.621418539,"remaining_time":0.1145756141},
{"learn":[1.589659312],"iteration":934,"passed_time":1.622862666,"remaining_time":0.1128193297},
{"learn":[1.589461329],"iteration":935,"passed_time":1.624310321,"remaining_time":0.1110639536},
{"learn":[1.589023307],"iteration":936,"passed_time":1.626040968,"remaining_time":0.1093282615},
{"learn":[1.588702153],"iteration":937,"passed_time":1.627542871,"remaining_time":0.1075774605},
{"learn":[1.588190106],"iteration":938,"passed_time":1.629013881,"remaining_time":0.1058251829},
{"learn":[1.587688552],"iteration":939,"passed_time":1.630416393,"remaining_time":0.1040691315},
{"learn":[1.587317225],"iteration":940,"passed_time":1.631909285,"remaining_time":0.1023194982},
{"learn":[1.58674808],"iteration":941,"passed_time":1.633380296,"remaining_time":0.1005690628},
{"learn":[1.586372125],"iteration":942,"passed_time":1.634810391,"remaining_time":0.09881674683},
{"learn":[1.586050269],"iteration":943,"passed_time":1.636328026,"remaining_time":0.09707030666},
{"learn":[1.585653118],"iteration":944,"passed_time":1.63787478,"remaining_time":0.0953260454},
{"learn":[1.585295806],"iteration":945,"passed_time":1.639269974,"remaining_time":0.09357355029},
{"learn":[1.584965734],"iteration":946,"passed_time":1.640756613,"remaining_time":0.09182692763},
{"learn":[1.584632959],"iteration":947,"passed_time":1.642218508,"remaining_time":0.09007949624},
{"learn":[1.584236541],"iteration":948,"passed_time":1.643709146,"remaining_time":0.08833421122},
{"learn":[1.583911364],"iteration":949,"passed_time":1.645168578,"remaining_time":0.08658781989},
{"learn":[1.583698573],"iteration":950,"passed_time":1.646577594,"remaining_time":0.08483943441},
{"learn":[1.583367164],"iteration":951,"passed_time":1.648115515,"remaining_time":0.08309826128},
{"learn":[1.583110234],"iteration":952,"passed_time":1.649572901,"remaining_time":0.08135354287},
{"learn":[1.582803997],"iteration":953,"passed_time":1.650963209,"remaining_time":0.07960619245},
{"learn":[1.582539827],"iteration":954,"passed_time":1.652430554,"remaining_time":0.07786321983},
{"learn":[1.58221875],"iteration":955,"passed_time":1.653864575,"remaining_time":0.07611929005},
{"learn":[1.581952891],"iteration":956,"passed_time":1.655290797,"remaining_time":0.07437565752},
{"learn":[1.58167104],"iteration":957,"passed_time":1.656733796,"remaining_time":0.07263342319},
{"learn":[1.581379632],"iteration":958,"passed_time":1.658124709,"remaining_time":0.07088958609},
{"learn":[1.581185529],"iteration":959,"passed_time":1.659545721,"remaining_time":0.06914773837},
{"learn":[1.580718622],"iteration":960,"passed_time":1.661040075,"remaining_time":0.06740953479},
{"learn":[1.580232388],"iteration":961,"passed_time":1.662424087,"remaining_time":0.06566747954},
{"learn":[1.579813356],"iteration":962,"passed_time":1.663965683,"remaining_time":0.06393222252},
{"learn":[1.579382156],"iteration":963,"passed_time":1.665483956,"remaining_time":0.06219649628},
{"learn":[1.579163071],"iteration":964,"passed_time":1.666905699,"remaining_time":0.06045771965},
{"learn":[1.578675006],"iteration":965,"passed_time":1.668401285,"remaining_time":0.05872219844},
{"learn":[1.578309528],"iteration":966,"passed_time":1.669886515,"remaining_time":0.05698682005},
{"learn":[1.578036242],"iteration":967,"passed_time":1.671259053,"remaining_time":0.05524823316},
{"learn":[1.577931],"iteration":968,"passed_time":1.672689785,"remaining_time":0.05351226351},
{"learn":[1.577631125],"iteration":969,"passed_time":1.67410303,"remaining_time":0.05177638236},
{"learn":[1.577385783],"iteration":970,"passed_time":1.675468803,"remaining_time":0.05003974797},
{"learn":[1.577106885],"iteration":971,"passed_time":1.676880293,"remaining_time":0.04830519364},
{"learn":[1.576806008],"iteration":972,"passed_time":1.678360762,"remaining_time":0.04657321746},
{"learn":[1.576554021],"iteration":973,"passed_time":1.679822502,"remaining_time":0.04484125774},
{"learn":[1.576280695],"iteration":974,"passed_time":1.681190373,"remaining_time":0.04310744547},
{"learn":[1.575979504],"iteration":975,"passed_time":1.682657479,"remaining_time":0.04137682325},
{"learn":[1.575718267],"iteration":976,"passed_time":1.684144995,"remaining_time":0.03964722096},
{"learn":[1.575553458],"iteration":977,"passed_time":1.685414749,"remaining_time":0.03791321522},
{"learn":[1.575334222],"iteration":978,"passed_time":1.686856997,"remaining_time":0.03618385795},
{"learn":[1.574949652],"iteration":979,"passed_time":1.68854441,"remaining_time":0.03446009},
{"learn":[1.574810538],"iteration":980,"passed_time":1.690002516,"remaining_time":0.03273195495},
{"learn":[1.5744506],"iteration":981,"passed_time":1.691608038,"remaining_time":0.03100707197},
{"learn":[1.574227064],"iteration":982,"passed_time":1.692999306,"remaining_time":0.02927872655},
{"learn":[1.573920587],"iteration":983,"passed_time":1.694546372,"remaining_time":0.02755359955},
{"learn":[1.573552426],"iteration":984,"passed_time":1.696083949,"remaining_time":0.02582868958},
{"learn":[1.573213803],"iteration":985,"passed_time":1.697479706,"remaining_time":0.02410214593},
{"learn":[1.572815509],"iteration":986,"passed_time":1.698924209,"remaining_time":0.0223769146},
{"learn":[1.572566391],"iteration":987,"passed_time":1.700497272,"remaining_time":0.02065381301},
{"learn":[1.572241591],"iteration":988,"passed_time":1.70195164,"remaining_time":0.01892969468},
{"learn":[1.5719605],"iteration":989,"passed_time":1.703370355,"remaining_time":0.01720576116},
{"learn":[1.571575979],"iteration":990,"passed_time":1.704833045,"remaining_time":0.01548284299},
{"learn":[1.571317906],"iteration":991,"passed_time":1.706327691,"remaining_time":0.01376070719},
{"learn":[1.570872555],"iteration":992,"passed_time":1.707785286,"remaining_time":0.01203876838},
{"learn":[1.570561563],"iteration":993,"passed_time":1.709241753,"remaining_time":0.01031735464},
{"learn":[1.570243944],"iteration":994,"passed_time":1.7107044,"remaining_time":0.008596504523},
{"learn":[1.569864342],"iteration":995,"passed_time":1.712228885,"remaining_time":0.006876421224},
{"learn":[1.569633845],"iteration":996,"passed_time":1.713608209,"remaining_time":0.005156293508},
{"learn":[1.569442305],"iteration":997,"passed_time":1.715010606,"remaining_time":0.003436895003},
{"learn":[1.569103756],"iteration":998,"passed_time":1.71654455,"remaining_time":0.001718262813},
{"learn":[1.568844533],"iteration":999,"passed_time":1.717933323,"remaining_time":0}
]}